Workbook

Sheet Yearly
A1: Year | B1: Nifty 50 | C1: Nifty PE | D1: Nifty PB | E1: 10yr Yeild | F1: Buffett Indicator | G1: Earning Yeild | H1: BEER ratio | I1: Percentile | M1: Valuation Score | N1: Nifty | O1: Nifty aft 5yr | P1: Future 5yr CAGR
I2: PE | J2: PB | K2: BEER | L2: Buffett
A3: 2000 | B3: 1263.55 | C3: 19.2 | D3: 4.14 | E3: 0.1088 | F3: 48.17475 | G3: =(1/C3) -> 0.052083333 | H3: =G3/E3 -> 0.47870711 | I3: =_xlfn.PERCENTRANK.INC($C$3:$C$28,C3) -> 0.32 | J3: =_xlfn.PERCENTRANK.INC($D$3:$D$28,D3) -> 0.8 | K3: =_xlfn.PERCENTRANK.INC($H$3:$H$28,H3) -> 0.08 | L3: =_xlfn.PERCENTRANK.INC($F$3:$F$28,F3) -> 0.08 | M3: =(I3*0.4)+(J3*0.2)+(K3*0.2)+((1-L3)*0.2) -> 0.488 | N3: 1263.55 | O3: 2836.55 | P3: =(O3/N3)^(1/5)-1 -> 0.17554593
A4: 2001 | B4: 1059.05 | C4: 15.35 | D4: 2.38 | E4: 0.07939 | F4: 30.646752 | G4: =(1/C4) -> 0.06514658 | H4: =G4/E4 -> 0.82058924 | I4: =_xlfn.PERCENTRANK.INC($C$3:$C$28,C4) -> 0.12 | J4: =_xlfn.PERCENTRANK.INC($D$3:$D$28,D4) -> 0 | K4: =_xlfn.PERCENTRANK.INC($H$3:$H$28,H4) -> 0.84 | L4: =_xlfn.PERCENTRANK.INC($F$3:$F$28,F4) -> 0 | M4: =(I4*0.4)+(J4*0.2)+(K4*0.2)+((1-L4)*0.2) -> 0.416 | N4: 1059.05 | O4: 3966.4 | P4: =(O4/N4)^(1/5)-1 -> 0.30225493
A5: 2002 | B5: 1093.5 | C5: 14.83 | D5: 2.39 | E5: 0.06083 | F5: 33.438061 | G5: =(1/C5) -> 0.067430883 | H5: =G5/E5 -> 1.1085136 | I5: =_xlfn.PERCENTRANK.INC($C$3:$C$28,C5) -> 0.04 | J5: =_xlfn.PERCENTRANK.INC($D$3:$D$28,D5) -> 0.04 | K5: =_xlfn.PERCENTRANK.INC($H$3:$H$28,H5) -> 0.96 | L5: =_xlfn.PERCENTRANK.INC($F$3:$F$28,F5) -> 0.04 | M5: =(I5*0.4)+(J5*0.2)+(K5*0.2)+((1-L5)*0.2) -> 0.408 | N5: 1093.5 | O5: 6138.6 | P5: =(O5/N5)^(1/5)-1 -> 0.41205011
A6: 2003 | B6: 1879.75 | C6: 20.73 | D6: 4.05 | E6: 0.05122 | F6: 50.846571 | G6: =(1/C6) -> 0.048239267 | H6: =G6/E6 -> 0.94180529 | I6: =_xlfn.PERCENTRANK.INC($C$3:$C$28,C6) -> 0.36 | J6: =_xlfn.PERCENTRANK.INC($D$3:$D$28,D6) -> 0.76 | K6: =_xlfn.PERCENTRANK.INC($H$3:$H$28,H6) -> 0.88 | L6: =_xlfn.PERCENTRANK.INC($F$3:$F$28,F6) -> 0.12 | M6: =(I6*0.4)+(J6*0.2)+(K6*0.2)+((1-L6)*0.2) -> 0.648 | N6: 1879.75 | O6: 2959.15 | P6: =(O6/N6)^(1/5)-1 -> 0.09499813
A7: 2004 | B7: 2080.5 | C7: 15.32 | D7: 3.61 | E7: 0.06706 | F7: 58.597294 | G7: =(1/C7) -> 0.065274151 | H7: =G7/E7 -> 0.97336939 | I7: =_xlfn.PERCENTRANK.INC($C$3:$C$28,C7) -> 0.08 | J7: =_xlfn.PERCENTRANK.INC($D$3:$D$28,D7) -> 0.52 | K7: =_xlfn.PERCENTRANK.INC($H$3:$H$28,H7) -> 0.92 | L7: =_xlfn.PERCENTRANK.INC($F$3:$F$28,F7) -> 0.16 | M7: =(I7*0.4)+(J7*0.2)+(K7*0.2)+((1-L7)*0.2) -> 0.488 | N7: 2080.5 | O7: 5201.05 | P7: =(O7/N7)^(1/5)-1 -> 0.2011152
A8: 2005 | B8: 2836.55 | C8: 17.16 | D8: 4.37 | E8: 0.0711 | F8: 76.152115 | G8: =(1/C8) -> 0.058275058 | H8: =G8/E8 -> 0.81962107 | I8: =_xlfn.PERCENTRANK.INC($C$3:$C$28,C8) -> 0.2 | J8: =_xlfn.PERCENTRANK.INC($D$3:$D$28,D8) -> 0.88 | K8: =_xlfn.PERCENTRANK.INC($H$3:$H$28,H8) -> 0.8 | L8: =_xlfn.PERCENTRANK.INC($F$3:$F$28,F8) -> 0.4 | M8: =(I8*0.4)+(J8*0.2)+(K8*0.2)+((1-L8)*0.2) -> 0.536 | N8: 2836.55 | O8: 6134.5 | P8: =(O8/N8)^(1/5)-1 -> 0.16680356
A9: 2006 | B9: 3966.4 | C9: 21.26 | D9: 5.07 | E9: 0.07619 | F9: 95.215152 | G9: =(1/C9) -> 0.047036689 | H9: =G9/E9 -> 0.6173604 | I9: =_xlfn.PERCENTRANK.INC($C$3:$C$28,C9) -> 0.44 | J9: =_xlfn.PERCENTRANK.INC($D$3:$D$28,D9) -> 0.96 | K9: =_xlfn.PERCENTRANK.INC($H$3:$H$28,H9) -> 0.48 | L9: =_xlfn.PERCENTRANK.INC($F$3:$F$28,F9) -> 0.56 | M9: =(I9*0.4)+(J9*0.2)+(K9*0.2)+((1-L9)*0.2) -> 0.552 | N9: 3966.4 | O9: 4624.3 | P9: =(O9/N9)^(1/5)-1 -> 0.031169119
A10: 2007 | B10: 6138.6 | C10: 27.62 | D10: 6.39 | E10: 0.07791 | F10: 161.23945 | G10: =(1/C10) -> 0.036205648 | H10: =G10/E10 -> 0.46471118 | I10: =_xlfn.PERCENTRANK.INC($C$3:$C$28,C10) -> 0.92 | J10: =_xlfn.PERCENTRANK.INC($D$3:$D$28,D10) -> 1 | K10: =_xlfn.PERCENTRANK.INC($H$3:$H$28,H10) -> 0.04 | L10: =_xlfn.PERCENTRANK.INC($F$3:$F$28,F10) -> 1 | M10: =(I10*0.4)+(J10*0.2)+(K10*0.2)+((1-L10)*0.2) -> 0.576 | N10: 6138.6 | O10: 5905.1 | P10: =(O10/N10)^(1/5)-1 -> -0.0077260631
A11: 2008 | B11: 2959.15 | C11: 12.97 | D11: 2.44 | E11: 0.0526 | F11: 66.003104 | G11: =(1/C11) -> 0.077101002 | H11: =G11/E11 -> 1.4657985 | I11: =_xlfn.PERCENTRANK.INC($C$3:$C$28,C11) -> 0 | J11: =_xlfn.PERCENTRANK.INC($D$3:$D$28,D11) -> 0.08 | K11: =_xlfn.PERCENTRANK.INC($H$3:$H$28,H11) -> 1 | L11: =_xlfn.PERCENTRANK.INC($F$3:$F$28,F11) -> 0.2 | M11: =(I11*0.4)+(J11*0.2)+(K11*0.2)+((1-L11)*0.2) -> 0.376 | N11: 2959.15 | O11: 6304 | P11: =(O11/N11)^(1/5)-1 -> 0.16329496
A12: 2009 | B12: 5201.05 | C12: 23.17 | D12: 3.65 | E12: 0.07679 | F12: 101.89449 | G12: =(1/C12) -> 0.043159258 | H12: =G12/E12 -> 0.56204268 | I12: =_xlfn.PERCENTRANK.INC($C$3:$C$28,C12) -> 0.68 | J12: =_xlfn.PERCENTRANK.INC($D$3:$D$28,D12) -> 0.56 | K12: =_xlfn.PERCENTRANK.INC($H$3:$H$28,H12) -> 0.28 | L12: =_xlfn.PERCENTRANK.INC($F$3:$F$28,F12) -> 0.72 | M12: =(I12*0.4)+(J12*0.2)+(K12*0.2)+((1-L12)*0.2) -> 0.496 | N12: 5201.05 | O12: 8282.7 | P12: =(O12/N12)^(1/5)-1 -> 0.097529445
A13: 2010 | B13: 6134.5 | C13: 24.48 | D13: 3.87 | E13: 0.07913 | F13: 105.18295 | G13: =(1/C13) -> 0.040849673 | H13: =G13/E13 -> 0.51623497 | I13: =_xlfn.PERCENTRANK.INC($C$3:$C$28,C13) -> 0.8 | J13: =_xlfn.PERCENTRANK.INC($D$3:$D$28,D13) -> 0.68 | K13: =_xlfn.PERCENTRANK.INC($H$3:$H$28,H13) -> 0.16 | L13: =_xlfn.PERCENTRANK.INC($F$3:$F$28,F13) -> 0.76 | M13: =(I13*0.4)+(J13*0.2)+(K13*0.2)+((1-L13)*0.2) -> 0.536 | N13: 6134.5 | O13: 7964.35 | P13: =(O13/N13)^(1/5)-1 -> 0.053596291
A14: 2011 | B14: 4624.3 | C14: 16.75 | D14: 2.76 | E14: 0.0856 | F14: 68.270064 | G14: =(1/C14) -> 0.059701493 | H14: =G14/E14 -> 0.69744734 | I14: =_xlfn.PERCENTRANK.INC($C$3:$C$28,C14) -> 0.16 | J14: =_xlfn.PERCENTRANK.INC($D$3:$D$28,D14) -> 0.12 | K14: =_xlfn.PERCENTRANK.INC($H$3:$H$28,H14) -> 0.72 | L14: =_xlfn.PERCENTRANK.INC($F$3:$F$28,F14) -> 0.28 | M14: =(I14*0.4)+(J14*0.2)+(K14*0.2)+((1-L14)*0.2) -> 0.376 | N14: 4624.3 | O14: 8185.8 | P14: =(O14/N14)^(1/5)-1 -> 0.12099332
... A23: 2020 | B23: 13981.75 | C23: 38.45 | D23: 3.96 | E23: 0.05894 | F23: 95.424502 | G23: =(1/C23) -> 0.026007802 | H23: =G23/E23 -> 0.44125895 | I23: =_xlfn.PERCENTRANK.INC($C$3:$C$28,C23) -> 1 | J23: =_xlfn.PERCENTRANK.INC($D$3:$D$28,D23) -> 0.72 | K23: =_xlfn.PERCENTRANK.INC($H$3:$H$28,H23) -> 0 | L23: =_xlfn.PERCENTRANK.INC($F$3:$F$28,F23) -> 0.6 | M23: =(I23*0.4)+(J23*0.2)+(K23*0.2)+((1-L23)*0.2) -> 0.624 | N23: 13981.75 | O23: 26129.6 | P23: =(O23/N23)^(1/5)-1 -> 0.13322004
A24: 2021 | B24: 17354.05 | C24: 24.11 | D24: 4.37 | E24: 0.06454 | F24: 112.02132 | G24: =(1/C24) -> 0.041476566 | H24: =G24/E24 -> 0.64264899 | I24: =_xlfn.PERCENTRANK.INC($C$3:$C$28,C24) -> 0.76 | J24: =_xlfn.PERCENTRANK.INC($D$3:$D$28,D24) -> 0.88 | K24: =_xlfn.PERCENTRANK.INC($H$3:$H$28,H24) -> 0.56 | L24: =_xlfn.PERCENTRANK.INC($F$3:$F$28,F24) -> 0.8 | M24: =(I24*0.4)+(J24*0.2)+(K24*0.2)+((1-L24)*0.2) -> 0.632 | N24: 17354.05
A25: 2022 | B25: 18105.3 | C25: 21.79 | D25: 4.25 | E25: 0.07327 | F25: 101.23306 | G25: =(1/C25) -> 0.045892611 | H25: =G25/E25 -> 0.62634927 | I25: =_xlfn.PERCENTRANK.INC($C$3:$C$28,C25) -> 0.52 | J25: =_xlfn.PERCENTRANK.INC($D$3:$D$28,D25) -> 0.84 | K25: =_xlfn.PERCENTRANK.INC($H$3:$H$28,H25) -> 0.52 | L25: =_xlfn.PERCENTRANK.INC($F$3:$F$28,F25) -> 0.68 | M25: =(I25*0.4)+(J25*0.2)+(K25*0.2)+((1-L25)*0.2) -> 0.544 | N25: 18105.3
A26: 2023 | B26: 21731.4 | C26: 23.17 | D26: 3.83 | E26: 0.07176 | F26: 119.28387 | G26: =(1/C26) -> 0.043159258 | H26: =G26/E26 -> 0.60143893 | I26: =_xlfn.PERCENTRANK.INC($C$3:$C$28,C26) -> 0.68 | J26: =_xlfn.PERCENTRANK.INC($D$3:$D$28,D26) -> 0.64 | K26: =_xlfn.PERCENTRANK.INC($H$3:$H$28,H26) -> 0.36 | L26: =_xlfn.PERCENTRANK.INC($F$3:$F$28,F26) -> 0.84 | M26: =(I26*0.4)+(J26*0.2)+(K26*0.2)+((1-L26)*0.2) -> 0.504 | N26: 21731.4
A27: 2024 | B27: 23644.8 | C27: 21.79 | D27: 3.53 | E27: 0.06759 | F27: 131.24143 | G27: =(1/C27) -> 0.045892611 | H27: =G27/E27 -> 0.67898522 | I27: =_xlfn.PERCENTRANK.INC($C$3:$C$28,C27) -> 0.52 | J27: =_xlfn.PERCENTRANK.INC($D$3:$D$28,D27) -> 0.4 | K27: =_xlfn.PERCENTRANK.INC($H$3:$H$28,H27) -> 0.68 | L27: =_xlfn.PERCENTRANK.INC($F$3:$F$28,F27) -> 0.88 | M27: =(I27*0.4)+(J27*0.2)+(K27*0.2)+((1-L27)*0.2) -> 0.448 | N27: 23644.8
A28: 2025 | B28: 26129.6 | C28: 22.75 | D28: 3.55 | E28: 0.06588 | F28: 137.7 | G28: =(1/C28) -> 0.043956044 | H28: =G28/E28 -> 0.66721378 | I28: =_xlfn.PERCENTRANK.INC($C$3:$C$28,C28) -> 0.64 | J28: =_xlfn.PERCENTRANK.INC($D$3:$D$28,D28) -> 0.44 | K28: =_xlfn.PERCENTRANK.INC($H$3:$H$28,H28) -> 0.64 | L28: =_xlfn.PERCENTRANK.INC($F$3:$F$28,F28) -> 0.92 | M28: =(I28*0.4)+(J28*0.2)+(K28*0.2)+((1-L28)*0.2) -> 0.488 | N28: 26129.6

Sheet Monthly
A1: S.no | B1: Date | C1: Market Cap | D1: US $ | E1: USD/INR | F1: Trillion | G1: Market Cap to GDP | H1: BEER | I1: Nifty 50 Earning Yield | J1: NIFTY 50 EPS | K1: India 10Yr Yield | L1: Nifty 50 | M1: Price to Book | N1: Equity Earnings Yield vs 10 Year G Sec Yield Gap | O1: Nifty 50 pe | P1: US 10yr Bond | Q1: India yr- US 10yr | R1: Dollar index | S1: PREITY Ratio | T1: 91 day T Bill | U1: Nifty Midcap 150 | V1: Midcap 150 PE | W1: Midcap EPS | X1: Midcap Earning Yield | Y1: Nifty Smallcap 250 | Z1: Smallcap 250 PE | AA1: Smallcap EPS | AB1: Smallcap Earning Yield
A2: 1 | B2: 37681 | C2: 537133 | D2: =C2/E2 -> 11312.826 | E2: 47.48 | F2: =(D2/100000) -> 0.11312826 | G2: =(F2/'Yearly GDP'!$B$2)*100 -> 21.969213 | H2: =(K2/I2) -> 0.8185672 | I2: =(J2/L2)*100 -> 7.4850299 | J2: =L2/O2 -> 73.218563 | K2: 6.127 | L2: 978.2 | M2: 2.15 | N2: =K2-I2 -> -1.3580299 | O2: 13.36 | P2: 3.802 | Q2: =K2-P2 -> 2.325 | R2: 99.49 | S2: =(O2*T2) -> 76.82 | T2: 5.75
A3: 2 | B3: 37712 | C3: 530630 | D3: =C3/E3 -> 11213.652 | E3: 47.32 | F3: =(D3/100000) -> 0.11213652 | G3: =(F3/'Yearly GDP'!$B$2)*100 -> 21.776618 | H3: =(K3/I3) -> 0.7728948 | I3: =(J3/L3)*100 -> 7.6103501 | J3: =L3/O3 -> 71.084475 | K3: 5.882 | L3: 934.05 | M3: 2.11 | N3: =K3-I3 -> -1.7283501 | O3: 13.14 | P3: 3.84 | Q3: =K3-P3 -> 2.042 | R3: 97.38 | S3: =(O3*T3) -> 60.444 | T3: 4.6
A4: 3 | B4: 37742 | C4: 612030 | D4: =C4/E4 -> 13016.376 | E4: 47.02 | F4: =(D4/100000) -> 0.13016376 | G4: =(F4/'Yearly GDP'!$B$2)*100 -> 25.277461 | H4: =(K4/I4) -> 0.6748845 | I4: =(J4/L4)*100 -> 8.583691 | J4: =L4/O4 -> 86.420601 | K4: 5.793 | L4: 1006.8 | M4: 2.17 | N4: =K4-I4 -> -2.790691 | O4: 11.65 | P4: 3.373 | Q4: =K4-P4 -> 2.42 | R4: 93.31 | S4: =(O4*T4) -> 54.056 | T4: 4.64
A5: 4 | B5: 37773 | C5: 678550 | D5: =C5/E5 -> 14620.771 | E5: 46.41 | F5: =(D5/100000) -> 0.14620771 | G5: =(F5/'Yearly GDP'!$B$2)*100 -> 28.393155 | H5: =(K5/I5) -> 0.742035 | I5: =(J5/L5)*100 -> 7.7220077 | J5: =L5/O5 -> 87.579151 | K5: 5.73 | L5: 1134.15 | M5: 2.44 | N5: =K5-I5 -> -1.9920077 | O5: 12.95 | P5: 3.516 | Q5: =K5-P5 -> 2.214 | R5: 95.11 | S5: =(O5*T5) -> 64.491 | T5: 4.98
A6: 5 | B6: 37803 | C6: 719145.05 | D6: =C6/E6 -> 15577.711 | E6: 46.165 | F6: =(D6/100000) -> 0.15577711 | G6: =(F6/'Yearly GDP'!$B$2)*100 -> 30.251508 | H6: =(K6/I6) -> 0.7210944 | I6: =(J6/L6)*100 -> 7.788162 | J6: =L6/O6 -> 92.355919 | K6: 5.616 | L6: 1185.85 | M6: 2.55 | N6: =K6-I6 -> -2.172162 | O6: 12.84 | P6: 4.41 | Q6: =K6-P6 -> 1.206 | R6: 97.14 | S6: =(O6*T6) -> 60.99 | T6: 4.75
A7: 6 | B7: 37834 | C7: 836651.05 | D7: =C7/E7 -> 18243.59 | E7: 45.86 | F7: =(D7/100000) -> 0.1824359 | G7: =(F7/'Yearly GDP'!$B$2)*100 -> 35.428575 | H7: =(K7/I7) -> 0.789659 | I7: =(J7/L7)*100 -> 6.6889632 | J7: =L7/O7 -> 90.73913 | K7: 5.282 | L7: 1356.55 | M7: 2.92 | N7: =K7-I7 -> -1.4069632 | O7: 14.95 | P7: 4.47 | Q7: =K7-P7 -> 0.812 | R7: 98.1 | S7: =(O7*T7) -> 69.5175 | T7: 4.65
A8: 7 | B8: 37865 | C8: 863481 | D8: =C8/E8 -> 18915.246 | E8: 45.65 | F8: =(D8/100000) -> 0.18915246 | G8: =(F8/'Yearly GDP'!$B$2)*100 -> 36.732913 | H8: =(K8/I8) -> 0.8076614 | I8: =(J8/L8)*100 -> 6.4061499 | J8: =L8/O8 -> 90.78155 | K8: 5.174 | L8: 1417.1 | M8: 3.05 | N8: =K8-I8 -> -1.2321499 | O8: 15.61 | P8: 3.94 | Q8: =K8-P8 -> 1.234 | R8: 93.2 | S8: =(O8*T8) -> 70.5572 | T8: 4.52
A9: 8 | B9: 37895 | C9: 926748 | D9: =C9/E9 -> 20448.985 | E9: 45.32 | F9: =(D9/100000) -> 0.20448985 | G9: =(F9/'Yearly GDP'!$B$2)*100 -> 39.711394 | H9: =(K9/I9) -> 0.87465 | I9: =(J9/L9)*100 -> 5.8309038 | J9: =L9/O9 -> 90.723032 | K9: 5.1 | L9: 1555.9 | M9: 3.35 | N9: =K9-I9 -> -0.73090379 | O9: 17.15 | P9: 4.297 | Q9: =K9-P9 -> 0.803 | R9: 92.88 | S9: =(O9*T9) -> 78.0325 | T9: 4.55
A10: 9 | B10: 37926 | C10: 979541 | D10: =C10/E10 -> 21401.376 | E10: 45.77 | F10: =(D10/100000) -> 0.21401376 | G10: =(F10/'Yearly GDP'!$B$2)*100 -> 41.560913 | H10: =(K10/I10) -> 0.9166807 | I10: =(J10/L10)*100 -> 5.6148231 | J10: =L10/O10 -> 90.693431 | K10: 5.147 | L10: 1615.25 | M10: 3.47 | N10: =K10-I10 -> -0.46782313 | O10: 17.81 | P10: 4.334 | Q10: =K10-P10 -> 0.813 | R10: 90.28 | S10: =(O10*T10) -> 75.6925 | T10: 4.25
A11: 10 | B11: 37956 | C11: 1167029 | D11: =C11/E11 -> 25578.718 | E11: 45.625 | F11: =(D11/100000) -> 0.25578718 | G11: =(F11/'Yearly GDP'!$B$2)*100 -> 49.6732 | H11: =(K11/I11) -> 1.0617906 | I11: =(J11/L11)*100 -> 4.8239267 | J11: =L11/O11 -> 90.677762 | K11: 5.122 | L11: 1879.75 | M11: 4.05 | N11: =K11-I11 -> 0.29807332 | O11: 20.73 | P11: 4.253 | Q11: =K11-P11 -> 0.869 | R11: 87.26 | S11: =(O11*T11) -> 87.8952 | T11: 4.24
A12: 11 | B12: 37987 | C12: 1116150 | D12: =C12/E12 -> 24655.401 | E12: 45.27 | F12: =(D12/100000) -> 0.24655401 | G12: =(F12/'Yearly GDP'!$B$3)*100 -> 40.571665 | H12: =(K12/I12) -> 1.0395168 | I12: =(J12/L12)*100 -> 5.01002 | J12: =L12/O12 -> 90.668838 | K12: 5.208 | L12: 1809.75 | M12: 3.9 | N12: =K12-I12 -> 0.19797996 | O12: 19.96 | P12: 4.134 | Q12: =K12-P12 -> 1.074 | R12: 87.42 | S12: =(O12*T12) -> 86.4268 | T12: 4.33
A13: 12 | B13: 38018 | C13: 1110954 | D13: =C13/E13 -> 24575.91 | E13: 45.205 | F13: =(D13/100000) -> 0.2457591 | G13: =(F13/'Yearly GDP'!$B$3)*100 -> 40.440859 | H13: =(K13/I13) -> 1.039311 | I13: =(J13/L13)*100 -> 5.0658561 | J13: =L13/O13 -> 91.200608 | K13: 5.265 | L13: 1800.3 | M13: 3.89 | N13: =K13-I13 -> 0.19914387 | O13: 19.74 | P13: 3.972 | Q13: =K13-P13 -> 1.293 | R13: 87.42 | S13: =(O13*T13) -> 85.4742 | T13: 4.33
A14: 13 | B14: 38047 | C14: 1120976 | D14: =C14/E14 -> 25858.731 | E14: 43.35 | F14: =(D14/100000) -> 0.25858731 | G14: =(F14/'Yearly GDP'!$B$3)*100 -> 42.551804 | H14: =(K14/I14) -> 1.065429 | I14: =(J14/L14)*100 -> 4.8309179 | J14: =L14/O14 -> 85.599034 | K14: 5.147 | L14: 1771.9 | M14: 3.5 | N14: =K14-I14 -> 0.31608213 | O14: 20.7 | P14: 3.837 | Q14: =K14-P14 -> 1.31 | R14: 87.95 | S14: =(O14*T14) -> 88.596 | T14: 4.28
A15: 14 | B15: 38078 | C15: 1171828 | D15: =C15/E15 -> 26350.978 | E15: 44.47 | F15: =(D15/100000) -> 0.26350978 | G15: =(F15/'Yearly GDP'!$B$3)*100 -> 43.36182 | H15: =(K15/I15) -> 0.9558556 | I15: =(J15/L15)*100 -> 5.3533191 | J15: =L15/O15 -> 96.150964 | K15: 5.117 | L15: 1796.1 | M15: 3.54 | N15: =K15-I15 -> -0.23631906 | O15: 18.68 | P15: 4.51 | Q15: =K15-P15 -> 0.607 | R15: 90.68 | S15: =(O15*T15) -> 81.258 | T15: 4.35
A16: 15 | B16: 38108 | C16: 950494 | D16: =C16/E16 -> 20899.164 | E16: 45.48 | F16: =(D16/100000) -> 0.20899164 | G16: =(F16/'Yearly GDP'!$B$3)*100 -> 34.390595 | H16: =(K16/I16) -> 0.6297156 | I16: =(J16/L16)*100 -> 8.3752094 | J16: =L16/O16 -> 124.25461 | K16: 5.274 | L16: 1483.6 | M16: 2.84 | N16: =K16-I16 -> -3.1012094 | O16: 11.94 | P16: 4.665 | Q16: =K16-P16 -> 0.609 | R16: 88.98 | S16: =(O16*T16) -> 52.0584 | T16: 4.36
A17: 16 | B17: 38139 | C17: 979700 | D17: =C17/E17 -> 21309.407 | E17: 45.975 | F17: =(D17/100000) -> 0.21309407 | G17: =(F17/'Yearly GDP'!$B$3)*100 -> 35.065669 | H17: =(K17/I17) -> 0.73944 | I17: =(J17/L17)*100 -> 7.9113924 | J17: =L17/O17 -> 119.11392 | K17: 5.85 | L17: 1505.6 | M17: 2.83 | N17: =K17-I17 -> -2.0613924 | O17: 12.64 | P17: 4.583 | Q17: =K17-P17 -> 1.267 | R17: 89 | S17: =(O17*T17) -> 56.248 | T17: 4.45
A18: 17 | B18: 38169 | C18: 1066087 | D18: =C18/E18 -> 22988.399 | E18: 46.375 | F18: =(D18/100000) -> 0.22988399 | G18: =(F18/'Yearly GDP'!$B$3)*100 -> 37.828532 | H18: =(K18/I18) -> 0.8401532 | I18: =(J18/L18)*100 -> 7.3367572 | J18: =L18/O18 -> 119.75789 | K18: 6.164 | L18: 1632.3 | M18: 2.95 | N18: =K18-I18 -> -1.1727572 | O18: 13.63 | P18: 4.491 | Q18: =K18-P18 -> 1.673 | R18: 90.11 | S18: =(O18*T18) -> 59.5631 | T18: 4.37
A19: 18 | B19: 38200 | C19: 1143074.9 | D19: =C19/E19 -> 24680.447 | E19: 46.315 | F19: =(D19/100000) -> 0.24680447 | G19: =(F19/'Yearly GDP'!$B$3)*100 -> 40.61288 | H19: =(K19/I19) -> 0.8305396 | I19: =(J19/L19)*100 -> 7.3313783 | J19: =L19/O19 -> 119.62977 | K19: 6.089 | L19: 1631.75 | M19: 2.95 | N19: =K19-I19 -> -1.2423783 | O19: 13.64 | P19: 4.24 | Q19: =K19-P19 -> 1.849 | R19: 88.96 | S19: =(O19*T19) -> 62.3348 | T19: 4.57
A20: 19 | B20: 38231 | C20: 1227550 | D20: =C20/E20 -> 26729.45 | E20: 45.925 | F20: =(D20/100000) -> 0.2672945 | G20: =(F20/'Yearly GDP'!$B$3)*100 -> 43.984614 | H20: =(K20/I20) -> 0.9109996 | I20: =(J20/L20)*100 -> 6.8540096 | J20: =L20/O20 -> 119.63674 | K20: 6.244 | L20: 1745.5 | M20: 3.16 | N20: =K20-I20 -> -0.6100096 | O20: 14.59 | P20: 4.123 | Q20: =K20-P20 -> 2.121 | R20: 87.51 | S20: =(O20*T20) -> 72.2205 | T20: 4.95
A21: 20 | B21: 38261 | C21: 1253825 | D21: =C21/E21 -> 27656.888 | E21: 45.335 | F21: =(D21/100000) -> 0.27656888 | G21: =(F21/'Yearly GDP'!$B$3)*100 -> 45.510758 | H21: =(K21/I21) -> 1.0243473 | I21: =(J21/L21)*100 -> 6.6979236 | J21: =L21/O21 -> 119.6852 | K21: 6.861 | L21: 1786.9 | M21: 3.08 | N21: =K21-I21 -> 0.16307636 | O21: 14.93 | P21: 4.029 | Q21: =K21-P21 -> 2.832 | R21: 84.98 | S21: =(O21*T21) -> 79.129 | T21: 5.3
A22: 21 | B22: 38292 | C22: 1446292 | D22: =C22/E22 -> 32500.944 | E22: 44.5 | F22: =(D22/100000) -> 0.32500944 | G22: =(F22/'Yearly GDP'!$B$3)*100 -> 53.481889 | H22: =(K22/I22) -> 1.1795883 | I22: =(J22/L22)*100 -> 6.1012813 | J22: =L22/O22 -> 119.5119 | K22: 7.197 | L22: 1958.8 | M22: 3.38 | N22: =K22-I22 -> 1.0957187 | O22: 16.39 | P22: 4.355 | Q22: =K22-P22 -> 2.842 | R22: 81.82 | S22: =(O22*T22) -> 85.228 | T22: 5.2
A23: 22 | B23: 38322 | C23: 1579161 | D23: =C23/E23 -> 36512.393 | E23: 43.25 | F23: =(D23/100000) -> 0.36512393 | G23: =(F23/'Yearly GDP'!$B$3)*100 -> 60.082924 | H23: =(K23/I23) -> 1.0273592 | I23: =(J23/L23)*100 -> 6.5274151 | J23: =L23/O23 -> 135.80287 | K23: 6.706 | L23: 2080.5 | M23: 3.61 | N23: =K23-I23 -> 0.17858486 | O23: 15.32 | P23: 4.222 | Q23: =K23-P23 -> 2.484 | R23: 81 | S23: =(O23*T23) -> 81.196 | T23: 5.3
A24: 23 | B24: 38353 | C24: 1557444 | D24: =C24/E24 -> 35684.362 | E24: 43.645 | F24: =(D24/100000) -> 0.35684362 | G24: =(F24/'Yearly GDP'!$B$4)*100 -> 50.319908 | H24: =(K24/I24) -> 0.9840004 | I24: =(J24/L24)*100 -> 6.8119891 | J24: =L24/O24 -> 140.16349 | K24: 6.703 | L24: 2057.6 | M24: 3.57 | N24: =K24-I24 -> -0.1089891 | O24: 14.68 | P24: 4.132 | Q24: =K24-P24 -> 2.571 | R24: 83.64 | S24: =(O24*T24) -> 76.336 | T24: 5.2
A25: 24 | B25: 38384 | C25: 1614597 | D25: =C25/E25 -> 37002.338 | E25: 43.635 | F25: =(D25/100000) -> 0.37002338 | G25: =(F25/'Yearly GDP'!$B$4)*100 -> 52.178436 | H25: =(K25/I25) -> 0.9836598 | I25: =(J25/L25)*100 -> 6.6577896 | J25: =L25/O25 -> 140.02996 | K25: 6.549 | L25: 2103.25 | M25: 3.92 | N25: =K25-I25 -> -0.10878961 | O25: 15.02 | P25: 4.381 | Q25: =K25-P25 -> 2.168 | R25: 82.51 | S25: =(O25*T25) -> 78.104 | T25: 5.2
A26: 25 | B26: 38412 | C26: 1585585 | D26: =C26/E26 -> 36304.179 | E26: 43.675 | F26: =(D26/100000) -> 0.36304179 | G26: =(F26/'Yearly GDP'!$B$4)*100 -> 51.193934 | H26: =(K26/I26) -> 0.974696 | I26: =(J26/L26)*100 -> 6.8493151 | J26: =L26/O26 -> 139.42808 | K26: 6.676 | L26: 2035.65 | M26: 3.82 | N26: =K26-I26 -> -0.17331507 | O26: 14.6 | P26: 4.488 | Q26: =K26-P26 -> 2.188 | R26: 84.05 | S26: =(O26*T26) -> 76.65 | T26: 5.25
A27: 26 | B27: 38443 | C27: 1517908 | D27: =C27/E27 -> 34950.679 | E27: 43.43 | F27: =(D27/100000) -> 0.34950679 | G27: =(F27/'Yearly GDP'!$B$4)*100 -> 49.285312 | H27: =(K27/I27) -> 0.9606153 | I27: =(J27/L27)*100 -> 7.535795 | J27: =L27/O27 -> 143.3685 | K27: 7.239 | L27: 1902.5 | M27: 3.56 | N27: =K27-I27 -> -0.29679503 | O27: 13.27 | P27: 4.2 | Q27: =K27-P27 -> 3.039 | R27: 84.42 | S27: =(O27*T27) -> 70.331 | T27: 5.3 | U27: 980.57 | Y27: 994.01
A28: 27 | B28: 38473 | C28: 1654994.9 | D28: =C28/E28 -> 37871.737 | E28: 43.7 | F28: =(D28/100000) -> 0.37871737 | G28: =(F28/'Yearly GDP'!$B$4)*100 -> 53.404409 | H28: =(K28/I28) -> 0.9728726 | I28: =(J28/L28)*100 -> 7.1736011 | J28: =L28/O28 -> 149.75251 | K28: 6.979 | L28: 2087.55 | M28: 3.91 | N28: =K28-I28 -> -0.19460115 | O28: 13.94 | P28: 3.987 | Q28: =K28-P28 -> 2.992 | R28: 87.8 | S28: =(O28*T28) -> 72.488 | T28: 5.2 | U28: 1054.85 | Y28: 1108.69
A29: 28 | B29: 38504 | C29: 1727502 | D29: =C29/E29 -> 39726.388 | E29: 43.485 | F29: =(D29/100000) -> 0.39726388 | G29: =(F29/'Yearly GDP'!$B$4)*100 -> 56.019726 | H29: =(K29/I29) -> 0.9883917 | I29: =(J29/L29)*100 -> 6.9881202 | J29: =L29/O29 -> 155.1782 | K29: 6.907 | L29: 2220.6 | M29: 3.98 | N29: =K29-I29 -> -0.081120196 | O29: 14.31 | P29: 3.921 | Q29: =K29-P29 -> 2.986 | R29: 88.98 | S29: =(O29*T29) -> 77.274 | T29: 5.4 | U29: 1064.61 | Y29: 1122.95
A30: 29 | B30: 38534 | C30: 1848740 | D30: =C30/E30 -> 42558.471 | E30: 43.44 | F30: =(D30/100000) -> 0.42558471 | G30: =(F30/'Yearly GDP'!$B$4)*100 -> 60.013356 | H30: =(K30/I30) -> 0.98136 | I30: =(J30/L30)*100 -> 7.0921986 | J30: =L30/O30 -> 163.99291 | K30: 6.96 | L30: 2312.3 | M30: 3.86 | N30: =K30-I30 -> -0.13219858 | O30: 14.1 | P30: 4.282 | Q30: =K30-P30 -> 2.678 | R30: 89.23 | S30: =(O30*T30) -> 74.73 | T30: 5.3 | U30: 1179.61 | Y30: 1255.36
A31: 30 | B31: 38565 | C31: 1957491 | D31: =C31/E31 -> 44473.27 | E31: 44.015 | F31: =(D31/100000) -> 0.4447327 | G31: =(F31/'Yearly GDP'!$B$4)*100 -> 62.713489 | H31: =(K31/I31) -> 1.0484932 | I31: =(J31/L31)*100 -> 6.7658999 | J31: =L31/O31 -> 161.34303 | K31: 7.094 | L31: 2384.65 | M31: 3.89 | N31: =K31-I31 -> 0.32810014 | O31: 14.78 | P31: 4.014 | Q31: =K31-P31 -> 3.08 | R31: 87.54 | S31: =(O31*T31) -> 76.856 | T31: 5.2 | U31: 1287.87 | Y31: 1465.98
A32: 31 | B32: 38596 | C32: 2098263 | D32: =C32/E32 -> 47736.617 | E32: 43.955 | F32: =(D32/100000) -> 0.47736617 | G32: =(F32/'Yearly GDP'!$B$4)*100 -> 67.315261 | H32: =(K32/I32) -> 1.1468115 | I32: =(J32/L32)*100 -> 6.1919505 | J32: =L32/O32 -> 161.0774 | K32: 7.101 | L32: 2601.4 | M32: 4.01 | N32: =K32-I32 -> 0.90904954 | O32: 16.15 | P32: 4.332 | Q32: =K32-P32 -> 2.769 | R32: 89.35 | S32: =(O32*T32) -> 86.241 | T32: 5.34 | U32: 1337.5 | Y32: 1463.97
A33: 32 | B33: 38626 | C33: 1927645 | D33: =C33/E33 -> 42770.024 | E33: 45.07 | F33: =(D33/100000) -> 0.42770024 | G33: =(F33/'Yearly GDP'!$B$4)*100 -> 60.311675 | H33: =(K33/I33) -> 1.0101877 | I33: =(J33/L33)*100 -> 7.0274069 | J33: =L33/O33 -> 166.6163 | K33: 7.099 | L33: 2370.95 | M33: 3.63 | N33: =K33-I33 -> 0.071593113 | O33: 14.23 | P33: 4.557 | Q33: =K33-P33 -> 2.542 | R33: 89.93 | S33: =(O33*T33) -> 78.6919 | T33: 5.53 | U33: 1214.03 | Y33: 1299.93
A34: 33 | B34: 38657 | C34: 2166823 | D34: =C34/E34 -> 47217.76 | E34: 45.89 | F34: =(D34/100000) -> 0.4721776 | G34: =(F34/'Yearly GDP'!$B$4)*100 -> 66.5836 | H34: =(K34/I34) -> 1.1297385 | I34: =(J34/L34)*100 -> 6.2695925 | J34: =L34/O34 -> 166.28527 | K34: 7.083 | L34: 2652.25 | M34: 4.06 | N34: =K34-I34 -> 0.81340752 | O34: 15.95 | P34: 4.49 | Q34: =K34-P34 -> 2.593 | R34: 91.51 | S34: =(O34*T34) -> 91.7125 | T34: 5.75 | U34: 1331.69 | Y34: 1455.22
A35: 34 | B35: 38687 | C35: 2322392 | D35: =C35/E35 -> 51614.446 | E35: 44.995 | F35: =(D35/100000) -> 0.51614446 | G35: =(F35/'Yearly GDP'!$B$4)*100 -> 72.783538 | H35: =(K35/I35) -> 1.220076 | I35: =(J35/L35)*100 -> 5.8275058 | J35: =L35/O35 -> 165.30012 | K35: 7.11 | L35: 2836.55 | M35: 4.37 | N35: =K35-I35 -> 1.2824942 | O35: 17.16 | P35: 4.395 | Q35: =K35-P35 -> 2.715 | R35: 90.96 | S35: =(O35*T35) -> 104.3328 | T35: 6.08 | U35: 1414.17 | Y35: 1537.75
A36: 35 | B36: 38718 | C36: 2434395 | D36: =C36/E36 -> 55421.628 | E36: 43.925 | F36: =(D36/100000) -> 0.55421628 | G36: =(F36/'Yearly GDP'!$B$5)*100 -> 67.556044 | H36: =(K36/I36) -> 1.319588 | I36: =(J36/L36)*100 -> 5.5865922 | J36: =L36/O36 -> 167.65922 | K36: 7.372 | L36: 3001.1 | M36: 4.53 | N36: =K36-I36 -> 1.7854078 | O36: 17.9 | P36: 4.519 | Q36: =K36-P36 -> 2.853 | R36: 88.81 | S36: =(O36*T36) -> 118.498 | T36: 6.62 | U36: 1511.78 | Y36: 1615.59
A37: 36 | B37: 38749 | C37: 2512083 | D37: =C37/E37 -> 56738.182 | E37: 44.275 | F37: =(D37/100000) -> 0.56738182 | G37: =(F37/'Yearly GDP'!$B$5)*100 -> 69.160855 | H37: =(K37/I37) -> 1.3507011 | I37: =(J37/L37)*100 -> 5.4734537 | J37: =L37/O37 -> 168.29228 | K37: 7.393 | L37: 3074.7 | M37: 4.64 | N37: =K37-I37 -> 1.9195463 | O37: 18.27 | P37: 4.557 | Q37: =K37-P37 -> 2.836 | R37: 90.08 | S37: =(O37*T37) -> 121.3128 | T37: 6.64 | U37: 1548.68 | Y37: 1601.12
A38: 37 | B38: 38777 | C38: 2813201 | D38: =C38/E38 -> 63218 | E38: 44.5 | F38: =(D38/100000) -> 0.63218 | G38: =(F38/'Yearly GDP'!$B$5)*100 -> 77.059411 | H38: =(K38/I38) -> 1.52963 | I38: =(J38/L38)*100 -> 4.9358342 | J38: =L38/O38 -> 167.94423 | K38: 7.55 | L38: 3402.55 | M38: 5.15 | N38: =K38-I38 -> 2.6141658 | O38: 20.26 | P38: 4.853 | Q38: =K38-P38 -> 2.697 | R38: 89.39 | S38: =(O38*T38) -> 123.586 | T38: 6.1 | U38: 1721.36 | Y38: 1762.19
A39: 38 | B39: 38808 | C39: 2990200 | D39: =C39/E39 -> 66596.882 | E39: 44.9 | F39: =(D39/100000) -> 0.66596882 | G39: =(F39/'Yearly GDP'!$B$5)*100 -> 81.178091 | H39: =(K39/I39) -> 1.500909 | I39: =(J39/L39)*100 -> 4.9236829 | J39: =L39/O39 -> 175.16494 | K39: 7.39 | L39: 3557.6 | M39: 5.39 | N39: =K39-I39 -> 2.4663171 | O39: 20.31 | P39: 5.057 | Q39: =K39-P39 -> 2.333 | R39: 85.88 | S39: =(O39*T39) -> 110.8926 | T39: 5.46 | U39: 1846.28 | Y39: 1977.06
A40: 39 | B40: 38838 | C40: 2612639 | D40: =C40/E40 -> 56422.395 | E40: 46.305 | F40: =(D40/100000) -> 0.56422395 | G40: =(F40/'Yearly GDP'!$B$5)*100 -> 68.775927 | H40: =(K40/I40) -> 1.3372614 | I40: =(J40/L40)*100 -> 5.7273769 | J40: =L40/O40 -> 175.89061 | K40: 7.659 | L40: 3071.05 | M40: 4.57 | N40: =K40-I40 -> 1.9316231 | O40: 17.46 | P40: 5.123 | Q40: =K40-P40 -> 2.536 | R40: 84.65 | S40: =(O40*T40) -> 100.7442 | T40: 5.77 | U40: 1568.17 | Y40: 1814.58
A41: 40 | B41: 38869 | C41: 2524659 | D41: =C41/E41 -> 55027.441 | E41: 45.88 | F41: =(D41/100000) -> 0.55027441 | G41: =(F41/'Yearly GDP'!$B$5)*100 -> 67.075552 | H41: =(K41/I41) -> 1.5030444 | I41: =(J41/L41)*100 -> 5.4229935 | J41: =L41/O41 -> 169.64208 | K41: 8.151 | L41: 3128.2 | M41: 4.66 | N41: =K41-I41 -> 2.7280065 | O41: 18.44 | P41: 5.145 | Q41: =K41-P41 -> 3.006 | R41: 84.9 | S41: =(O41*T41) -> 117.094 | T41: 6.35 | U41: 1388.44 | Y41: 1564.95
A42: 41 | B42: 38899 | C42: 2514261 | D42: =C42/E42 -> 54070.129 | E42: 46.5 | F42: =(D42/100000) -> 0.54070129 | G42: =(F42/'Yearly GDP'!$B$5)*100 -> 65.908639 | H42: =(K42/I42) -> 1.4531832 | I42: =(J42/L42)*100 -> 5.6689342 | J42: =L42/O42 -> 178.18594 | K42: 8.238 | L42: 3143.2 | M42: 4.29 | N42: =K42-I42 -> 2.5690658 | O42: 17.64 | P42: 4.988 | Q42: =K42-P42 -> 3.25 | R42: 85.09 | S42: =(O42*T42) -> 112.3668 | T42: 6.37 | U42: 1351.76 | Y42: 1545.83
A43: 42 | B43: 38930 | C43: 2777401 | D43: =C43/E43 -> 59754.755 | E43: 46.48 | F43: =(D43/100000) -> 0.59754755 | G43: =(F43/'Yearly GDP'!$B$5)*100 -> 72.837898 | H43: =(K43/I43) -> 1.5111265 | I43: =(J43/L43)*100 -> 5.2219321 | J43: =L43/O43 -> 178.27154 | K43: 7.891 | L43: 3413.9 | M43: 4.55 | N43: =K43-I43 -> 2.6690679 | O43: 19.15 | P43: 4.732 | Q43: =K43-P43 -> 3.159 | R43: 85.02 | S43: =(O43*T43) -> 121.6025 | T43: 6.35 | U43: 1501.38 | Y43: 1715.44
A44: 43 | B44: 38961 | C44: 2994132 | D44: =C44/E44 -> 65217.425 | E44: 45.91 | F44: =(D44/100000) -> 0.65217425 | G44: =(F44/'Yearly GDP'!$B$5)*100 -> 79.496606 | H44: =(K44/I44) -> 1.5987064 | I44: =(J44/L44)*100 -> 4.7801147 | J44: =L44/O44 -> 171.52964 | K44: 7.642 | L44: 3588.4 | M44: 4.76 | N44: =K44-I44 -> 2.8618853 | O44: 20.92 | P44: 4.633 | Q44: =K44-P44 -> 3.009 | R44: 85.68 | S44: =(O44*T44) -> 136.3984 | T44: 6.52 | U44: 1617.35 | Y44: 1820.15
A45: 44 | B45: 38991 | C45: 3138319 | D45: =C45/E45 -> 69864.626 | E45: 44.92 | F45: =(D45/100000) -> 0.69864626 | G45: =(F45/'Yearly GDP'!$B$5)*100 -> 85.161298 | H45: =(K45/I45) -> 1.5532125 | I45: =(J45/L45)*100 -> 4.9091802 | J45: =L45/O45 -> 183.80461 | K45: 7.625 | L45: 3744.1 | M45: 4.84 | N45: =K45-I45 -> 2.7158198 | O45: 20.37 | P45: 4.604 | Q45: =K45-P45 -> 3.021 | R45: 85.11 | S45: =(O45*T45) -> 136.479 | T45: 6.7 | U45: 1688.13 | Y45: 1900.48
A46: 45 | B46: 39022 | C46: 3373652 | D46: =C46/E46 -> 75642.422 | E46: 44.6 | F46: =(D46/100000) -> 0.75642422 | G46: =(F46/'Yearly GDP'!$B$5)*100 -> 92.204127 | H46: =(K46/I46) -> 1.5724032 | I46: =(J46/L46)*100 -> 4.7214353 | J46: =L46/O46 -> 186.70916 | K46: 7.424 | L46: 3954.5 | M46: 5.08 | N46: =K46-I46 -> 2.7025647 | O46: 21.18 | P46: 4.462 | Q46: =K46-P46 -> 2.962 | R46: 82.85 | S46: =(O46*T46) -> 140.4234 | T46: 6.63 | U46: 1762.01 | Y46: 1953.6
A47: 46 | B47: 39052 | C47: 3426000 | D47: =C47/E47 -> 77660.66 | E47: 44.115 | F47: =(D47/100000) -> 0.7766066 | G47: =(F47/'Yearly GDP'!$B$5)*100 -> 94.664253 | H47: =(K47/I47) -> 1.6197994 | I47: =(J47/L47)*100 -> 4.7036689 | J47: =L47/O47 -> 186.56632 | K47: 7.619 | L47: 3966.4 | M47: 5.07 | N47: =K47-I47 -> 2.9153311 | O47: 21.26 | P47: 4.7 | Q47: =K47-P47 -> 2.919 | R47: 83.43 | S47: =(O47*T47) -> 152.6468 | T47: 7.18 | U47: 1795.28 | Y47: 2014.87
A48: 47 | B48: 39083 | C48: 3571500 | D48: =C48/E48 -> 81023.14 | E48: 44.08 | F48: =(D48/100000) -> 0.8102314 | G48: =(F48/'Yearly GDP'!$B$6)*100 -> 86.170995 | H48: =(K48/I48) -> 1.535993 | I48: =(J48/L48)*100 -> 5.0377834 | J48: =L48/O48 -> 205.67758 | K48: 7.738 | L48: 4082.7 | M48: 5.2 | N48: =K48-I48 -> 2.7002166 | O48: 19.85 | P48: 4.814 | Q48: =K48-P48 -> 2.924 | R48: 84.43 | S48: =(O48*T48) -> 147.4855 | T48: 7.43 | U48: 1865.92 | Y48: 2162.23
A49: 48 | B49: 39114 | C49: 3296900 | D49: =C49/E49 -> 74776.593 | E49: 44.09 | F49: =(D49/100000) -> 0.74776593 | G49: =(F49/'Yearly GDP'!$B$6)*100 -> 79.52757 | H49: =(K49/I49) -> 1.4408 | I49: =(J49/L49)*100 -> 5.5524708 | J49: =L49/O49 -> 207.95669 | K49: 8 | L49: 3745.3 | M49: 4.77 | N49: =K49-I49 -> 2.4475292 | O49: 18.01 | P49: 4.577 | Q49: =K49-P49 -> 3.423 | R49: 83.5 | S49: =(O49*T49) -> 133.274 | T49: 7.4 | U49: 1711.55 | Y49: 2003.29
A50: 49 | B50: 39142 | C50: 3367400 | D50: =C50/E50 -> 78093.692 | E50: 43.12 | F50: =(D50/100000) -> 0.78093692 | G50: =(F50/'Yearly GDP'!$B$6)*100 -> 83.055423 | H50: =(K50/I50) -> 1.476048 | I50: =(J50/L50)*100 -> 5.4347826 | J50: =L50/O50 -> 207.69293 | K50: 8.022 | L50: 3821.55 | M50: 4.87 | N50: =K50-I50 -> 2.5872174 | O50: 18.4 | P50: 4.648 | Q50: =K50-P50 -> 3.374 | R50: 82.66 | S50: =(O50*T50) -> 138.92 | T50: 7.55 | U50: 1678.97 | Y50: 1938.26
A51: 50 | B51: 39173 | C51: 3650368 | D51: =C51/E51 -> 88935.753 | E51: 41.045 | F51: =(D51/100000) -> 0.88935753 | G51: =(F51/'Yearly GDP'!$B$6)*100 -> 94.586341 | H51: =(K51/I51) -> 1.5921004 | I51: =(J51/L51)*100 -> 5.1334702 | J51: =L51/O51 -> 209.85113 | K51: 8.173 | L51: 4087.9 | M51: 5.33 | N51: =K51-I51 -> 3.0395298 | O51: 19.48 | P51: 4.628 | Q51: =K51-P51 -> 3.545 | R51: 81.3 | S51: =(O51*T51) -> 144.152 | T51: 7.4 | U51: 1807.35 | Y51: 2093.89
A52: 51 | B52: 39203 | C52: 3898078 | D52: =C52/E52 -> 96546.824 | E52: 40.375 | F52: =(D52/100000) -> 0.96546824 | G52: =(F52/'Yearly GDP'!$B$6)*100 -> 102.68099 | H52: =(K52/I52) -> 1.649128 | I52: =(J52/L52)*100 -> 4.899559 | J52: =L52/O52 -> 210.47526 | K52: 8.08 | L52: 4295.8 | M52: 5.59 | N52: =K52-I52 -> 3.180441 | O52: 20.41 | P52: 4.892 | Q52: =K52-P52 -> 3.188 | R52: 82.25 | S52: =(O52*T52) -> 144.911 | T52: 7.1 | U52: 1911.86 | Y52: 2241.71
A53: 52 | B53: 39234 | C53: 3978381 | D53: =C53/E53 -> 98171.03 | E53: 40.525 | F53: =(D53/100000) -> 0.9817103 | G53: =(F53/'Yearly GDP'!$B$6)*100 -> 104.40839 | H53: =(K53/I53) -> 1.686522 | I53: =(J53/L53)*100 -> 4.8543689 | J53: =L53/O53 -> 209.62621 | K53: 8.187 | L53: 4318.3 | M53: 5.4 | N53: =K53-I53 -> 3.3326311 | O53: 20.6 | P53: 5.027 | Q53: =K53-P53 -> 3.16 | R53: 81.69 | S53: =(O53*T53) -> 149.35 | T53: 7.25 | U53: 2013.74 | Y53: 2346.62
A54: 53 | B54: 39264 | C54: 4317571 | D54: =C54/E54 -> 107428.99 | E54: 40.19 | F54: =(D54/100000) -> 1.0742899 | G54: =(F54/'Yearly GDP'!$B$6)*100 -> 114.25455 | H54: =(K54/I54) -> 1.6074405 | I54: =(J54/L54)*100 -> 4.8804295 | J54: =L54/O54 -> 221.02733 | K54: 7.845 | L54: 4528.85 | M54: 5.31 | N54: =K54-I54 -> 2.9645705 | O54: 20.49 | P54: 4.733 | Q54: =K54-P54 -> 3.112 | R54: 80.66 | S54: =(O54*T54) -> 128.0625 | T54: 6.25 | U54: 2067.11 | Y54: 2404.8
A55: 54 | B55: 39295 | C55: 4296994 | D55: =C55/E55 -> 105733.12 | E55: 40.64 | F55: =(D55/100000) -> 1.0573312 | G55: =(F55/'Yearly GDP'!$B$6)*100 -> 112.45094 | H55: =(K55/I55) -> 1.60186 | I55: =(J55/L55)*100 -> 4.950495 | J55: =L55/O55 -> 220.9901 | K55: 7.93 | L55: 4464 | M55: 5.08 | N55: =K55-I55 -> 2.979505 | O55: 20.2 | P55: 4.527 | Q55: =K55-P55 -> 3.403 | R55: 80.745 | S55: =(O55*T55) -> 139.38 | T55: 6.9 | U55: 2033.45 | Y55: 2399.88
A56: 55 | B56: 39326 | C56: 4886561 | D56: =C56/E56 -> 123211.32 | E56: 39.66 | F56: =(D56/100000) -> 1.2321132 | G56: =(F56/'Yearly GDP'!$B$6)*100 -> 131.03963 | H56: =(K56/I56) -> 1.789465 | I56: =(J56/L56)*100 -> 4.428698 | J56: =L56/O56 -> 222.38043 | K56: 7.925 | L56: 5021.35 | M56: 5.36 | N56: =K56-I56 -> 3.496302 | O56: 22.58 | P56: 4.594 | Q56: =K56-P56 -> 3.331 | R56: 77.625 | S56: =(O56*T56) -> 160.318 | T56: 7.1 | U56: 2309.83 | Y56: 2727.98
A57: 56 | B57: 39356 | C57: 5722227 | D57: =C57/E57 -> 145993.8 | E57: 39.195 | F57: =(D57/100000) -> 1.459938 | G57: =(F57/'Yearly GDP'!$B$6)*100 -> 155.26961 | H57: =(K57/I57) -> 2.0177586 | I57: =(J57/L57)*100 -> 3.8850039 | J57: =L57/O57 -> 229.24048 | K57: 7.839 | L57: 5900.65 | M57: 6.18 | N57: =K57-I57 -> 3.9539961 | O57: 25.74 | P57: 4.473 | Q57: =K57-P57 -> 3.366 | R57: 76.46 | S57: =(O57*T57) -> 186.615 | T57: 7.25 | U57: 2555.73 | Y57: 3027.42
A58: 57 | B58: 39387 | C58: 5876742 | D58: =C58/E58 -> 148702.99 | E58: 39.52 | F58: =(D58/100000) -> 1.4870299 | G58: =(F58/'Yearly GDP'!$B$6)*100 -> 158.15092 | H58: =(K58/I58) -> 1.9928505 | I58: =(J58/L58)*100 -> 3.9666799 | J58: =L58/O58 -> 228.58985 | K58: 7.905 | L58: 5762.75 | M58: 6.05 | N58: =K58-I58 -> 3.9383201 | O58: 25.21 | P58: 3.949 | Q58: =K58-P58 -> 3.956 | R58: 76.17 | S58: =(O58*T58) -> 188.5708 | T58: 7.48 | U58: 2739.12 | Y58: 3301.78
A59: 58 | B59: 39417 | C59: 6543272 | D59: =C59/E59 -> 166051.82 | E59: 39.405 | F59: =(D59/100000) -> 1.6605182 | G59: =(F59/'Yearly GDP'!$B$6)*100 -> 176.60203 | H59: =(K59/I59) -> 2.1518742 | I59: =(J59/L59)*100 -> 3.6205648 | J59: =L59/O59 -> 222.25199 | K59: 7.791 | L59: 6138.6 | M59: 6.39 | N59: =K59-I59 -> 4.1704352 | O59: 27.62 | P59: 4.035 | Q59: =K59-P59 -> 3.756 | R59: 76.7 | S59: =(O59*T59) -> 203.8356 | T59: 7.38 | U59: 3162.15 | Y59: 3927.98
A60: 59 | B60: 39448 | C60: 5295387 | D60: =C60/E60 -> 134811.28 | E60: 39.28 | F60: =(D60/100000) -> 1.3481128 | G60: =(F60/'Yearly GDP'!$B$7)*100 -> 110.50105 | H60: =(K60/I60) -> 1.6541213 | I60: =(J60/L60)*100 -> 4.5516614 | J60: =L60/O60 -> 233.83933 | K60: 7.529 | L60: 5137.45 | M60: 5.38 | N60: =K60-I60 -> 2.9773386 | O60: 21.97 | P60: 3.597 | Q60: =K60-P60 -> 3.932 | R60: 75.285 | S60: =(O60*T60) -> 157.7446 | T60: 7.18 | U60: 2464.25 | Y60: 3030.27
A61: 60 | B61: 39479 | C61: 5419942 | D61: =C61/E61 -> 135770.09 | E61: 39.92 | F61: =(D61/100000) -> 1.3577009 | G61: =(F61/'Yearly GDP'!$B$7)*100 -> 111.28696 | H61: =(K61/I61) -> 1.6853936 | I61: =(J61/L61)*100 -> 4.4903458 | J61: =L61/O61 -> 234.55321 | K61: 7.568 | L61: 5223.5 | M61: 5.47 | N61: =K61-I61 -> 3.0776542 | O61: 22.27 | P61: 3.519 | Q61: =K61-P61 -> 4.049 | R61: 73.75 | S61: =(O61*T61) -> 164.3526 | T61: 7.38 | U61: 2440.62 | Y61: 2987.76
A62: 61 | B62: 39508 | C62: 4858122 | D62: =C62/E62 -> 121362.03 | E62: 40.03 | F62: =(D62/100000) -> 1.2136203 | G62: =(F62/'Yearly GDP'!$B$7)*100 -> 99.477073 | H62: =(K62/I62) -> 1.6376094 | I62: =(J62/L62)*100 -> 4.8473097 | J62: =L62/O62 -> 229.49588 | K62: 7.938 | L62: 4734.5 | M62: 5.09 | N62: =K62-I62 -> 3.0906903 | O62: 20.63 | P62: 3.421 | Q62: =K62-P62 -> 4.517 | R62: 72.165 | S62: =(O62*T62) -> 147.0919 | T62: 7.13 | U62: 2021.36 | Y62: 2520.87
A63: 62 | B63: 39539 | C63: 5442780 | D63: =C63/E63 -> 134522.49 | E63: 40.46 | F63: =(D63/100000) -> 1.3452249 | G63: =(F63/'Yearly GDP'!$B$7)*100 -> 110.26434 | H63: =(K63/I63) -> 1.7638452 | I63: =(J63/L63)*100 -> 4.5105999 | J63: =L63/O63 -> 233.01308 | K63: 7.956 | L63: 5165.9 | M63: 5.55 | N63: =K63-I63 -> 3.4454001 | O63: 22.17 | P63: 3.734 | Q63: =K63-P63 -> 4.222 | R63: 72.72 | S63: =(O63*T63) -> 161.841 | T63: 7.3 | U63: 2265.53 | Y63: 2780.28
A64: 63 | B64: 39569 | C64: 5098873 | D64: =C64/E64 -> 120941.01 | E64: 42.16 | F64: =(D64/100000) -> 1.2094101 | G64: =(F64/'Yearly GDP'!$B$7)*100 -> 99.131976 | H64: =(K64/I64) -> 1.6801474 | I64: =(J64/L64)*100 -> 4.8216008 | J64: =L64/O64 -> 234.81678 | K64: 8.101 | L64: 4870.1 | M64: 5.01 | N64: =K64-I64 -> 3.2793992 | O64: 20.74 | P64: 4.067 | Q64: =K64-P64 -> 4.034 | R64: 72.95 | S64: =(O64*T64) -> 153.8908 | T64: 7.42 | U64: 2127.69 | Y64: 2628.58
A65: 64 | B65: 39600 | C65: 4103651 | D65: =C65/E65 -> 95589.355 | E65: 42.93 | F65: =(D65/100000) -> 0.95589355 | G65: =(F65/'Yearly GDP'!$B$7)*100 -> 78.35193 | H65: =(K65/I65) -> 1.5056064 | I65: =(J65/L65)*100 -> 5.787037 | J65: =L65/O65 -> 233.82812 | K65: 8.713 | L65: 4040.55 | M65: 4 | N65: =K65-I65 -> 2.925963 | O65: 17.28 | P65: 3.975 | Q65: =K65-P65 -> 4.738 | R65: 72.8 | S65: =(O65*T65) -> 153.792 | T65: 8.9 | U65: 1649.12 | Y65: 2193.35
A66: 65 | B66: 39630 | C66: 4432427 | D66: =C66/E66 -> 104334.13 | E66: 42.483 | F66: =(D66/100000) -> 1.0433413 | G66: =(F66/'Yearly GDP'!$B$7)*100 -> 85.519782 | H66: =(K66/I66) -> 1.6973752 | I66: =(J66/L66)*100 -> 5.4884742 | J66: =L66/O66 -> 237.81284 | K66: 9.316 | L66: 4332.95 | M66: 3.99 | N66: =K66-I66 -> 3.8275258 | O66: 18.22 | P66: 3.958 | Q66: =K66-P66 -> 5.358 | R66: 73.42 | S66: =(O66*T66) -> 168.535 | T66: 9.25 | U66: 1751.12 | Y66: 2245.11
A67: 66 | B67: 39661 | C67: 4472461 | D67: =C67/E67 -> 101948.05 | E67: 43.87 | F67: =(D67/100000) -> 1.0194805 | G67: =(F67/'Yearly GDP'!$B$7)*100 -> 83.563976 | H67: =(K67/I67) -> 1.60341 | I67: =(J67/L67)*100 -> 5.425936 | J67: =L67/O67 -> 236.57081 | K67: 8.7 | L67: 4360 | M67: 3.83 | N67: =K67-I67 -> 3.274064 | O67: 18.43 | P67: 3.825 | Q67: =K67-P67 -> 4.875 | R67: 77.5 | S67: =(O67*T67) -> 165.87 | T67: 9 | U67: 1788.39 | Y67: 2301.79
A68: 67 | B68: 39692 | C68: 3900185 | D68: =C68/E68 -> 83310.584 | E68: 46.815 | F68: =(D68/100000) -> 0.83310584 | G68: =(F68/'Yearly GDP'!$B$7)*100 -> 68.287364 | H68: =(K68/I68) -> 1.4519645 | I68: =(J68/L68)*100 -> 5.9347181 | J68: =L68/O68 -> 232.71217 | K68: 8.617 | L68: 3921.2 | M68: 3.26 | N68: =K68-I68 -> 2.6822819 | O68: 16.85 | P68: 3.829 | Q68: =K68-P68 -> 4.788 | R68: 79.36 | S68: =(O68*T68) -> 145.7525 | T68: 8.65 | U68: 1495.38 | Y68: 1864.64
A69: 68 | B69: 39722 | C69: 2820388 | D69: =C69/E69 -> 57179.686 | E69: 49.325 | F69: =(D69/100000) -> 0.57179686 | G69: =(F69/'Yearly GDP'!$B$7)*100 -> 46.868595 | H69: =(K69/I69) -> 0.9399846 | I69: =(J69/L69)*100 -> 7.9554495 | J69: =L69/O69 -> 229.56245 | K69: 7.478 | L69: 2885.6 | M69: 2.42 | N69: =K69-I69 -> -0.47744948 | O69: 12.57 | P69: 3.97 | Q69: =K69-P69 -> 3.508 | R69: 86.345 | S69: =(O69*T69) -> 89.8755 | T69: 7.15 | U69: 1026.44 | Y69: 1264.1
A70: 69 | B70: 39753 | C70: 2653281 | D70: =C70/E70 -> 53520.545 | E70: 49.575 | F70: =(D70/100000) -> 0.53520545 | G70: =(F70/'Yearly GDP'!$B$7)*100 -> 43.869299 | H70: =(K70/I70) -> 0.855264 | I70: =(J70/L70)*100 -> 8.2781457 | J70: =L70/O70 -> 228.07119 | K70: 7.08 | L70: 2755.1 | M70: 2.32 | N70: =K70-I70 -> -1.1981457 | O70: 12.08 | P70: 2.92 | Q70: =K70-P70 -> 4.16 | R70: 86.705 | S70: =(O70*T70) -> 85.164 | T70: 7.05 | U70: 951.5 | Y70: 1111.02
A71: 70 | B71: 39783 | C71: 2916768 | D71: =C71/E71 -> 59991.115 | E71: 48.62 | F71: =(D71/100000) -> 0.59991115 | G71: =(F71/'Yearly GDP'!$B$7)*100 -> 49.173045 | H71: =(K71/I71) -> 0.682222 | I71: =(J71/L71)*100 -> 7.7101002 | J71: =L71/O71 -> 228.15343 | K71: 5.26 | L71: 2959.15 | M71: 2.44 | N71: =K71-I71 -> -2.4501002 | O71: 12.97 | P71: 2.22 | Q71: =K71-P71 -> 3.04 | R71: 82.15 | S71: =(O71*T71) -> 62.9045 | T71: 4.85 | U71: 1091.51 | Y71: 1214.54
A72: 71 | B72: 39814 | C72: 2798707 | D72: =C72/E72 -> 57291.853 | E72: 48.85 | F72: =(D72/100000) -> 0.57291853 | G72: =(F72/'Yearly GDP'!$B$8)*100 -> 47.743211 | H72: =(K72/I72) -> 0.829058 | I72: =(J72/L72)*100 -> 7.4626866 | J72: =L72/O72 -> 214.53731 | K72: 6.187 | L72: 2874.8 | M72: 2.39 | N72: =K72-I72 -> -1.2756866 | O72: 13.4 | P72: 2.851 | Q72: =K72-P72 -> 3.336 | R72: 86.46 | S72: =(O72*T72) -> 62.98 | T72: 4.7 | U72: 1005.7 | Y72: 1108.04
A73: 72 | B73: 39845 | C73: 2675622 | D73: =C73/E73 -> 52458.034 | E73: 51.005 | F73: =(D73/100000) -> 0.52458034 | G73: =(F73/'Yearly GDP'!$B$8)*100 -> 43.715028 | H73: =(K73/I73) -> 0.8302336 | I73: =(J73/L73)*100 -> 7.6219512 | J73: =L73/O73 -> 210.64405 | K73: 6.328 | L73: 2763.65 | M73: 2.29 | N73: =K73-I73 -> -1.2939512 | O73: 13.12 | P73: 3.021 | Q73: =K73-P73 -> 3.307 | R73: 88.15 | S73: =(O73*T73) -> 60.352 | T73: 4.6 | U73: 957.86 | Y73: 1036.28
A74: 73 | B74: 39873 | C74: 2896194 | D74: =C74/E74 -> 57270.991 | E74: 50.57 | F74: =(D74/100000) -> 0.57270991 | G74: =(F74/'Yearly GDP'!$B$8)*100 -> 47.725826 | H74: =(K74/I74) -> 1.0023006 | I74: =(J74/L74)*100 -> 6.9979006 | J74: =L74/O74 -> 211.40308 | K74: 7.014 | L74: 3020.95 | M74: 2.5 | N74: =K74-I74 -> 0.01609937 | O74: 14.29 | P74: 2.668 | Q74: =K74-P74 -> 4.346 | R74: 85.895 | S74: =(O74*T74) -> 67.163 | T74: 4.7 | U74: 1022.69 | Y74: 1116.81
A75: 74 | B75: 39904 | C75: 3375025 | D75: =C75/E75 -> 67649.329 | E75: 49.89 | F75: =(D75/100000) -> 0.67649329 | G75: =(F75/'Yearly GDP'!$B$8)*100 -> 56.37444 | H75: =(K75/I75) -> 1.0318026 | I75: =(J75/L75)*100 -> 6.0496068 | J75: =L75/O75 -> 210.16031 | K75: 6.242 | L75: 3473.95 | M75: 2.87 | N75: =K75-I75 -> 0.19239322 | O75: 16.53 | P75: 3.107 | Q75: =K75-P75 -> 3.135 | R75: 84.655 | S75: =(O75*T75) -> 55.3755 | T75: 3.35 | U75: 1195.9 | Y75: 1326.09
A76: 75 | B76: 39934 | C76: 4564572 | D76: =C76/E76 -> 96871.222 | E76: 47.12 | F76: =(D76/100000) -> 0.96871222 | G76: =(F76/'Yearly GDP'!$B$8)*100 -> 80.726019 | H76: =(K76/I76) -> 1.397022 | I76: =(J76/L76)*100 -> 4.803074 | J76: =L76/O76 -> 213.68636 | K76: 6.71 | L76: 4448.95 | M76: 3.63 | N76: =K76-I76 -> 1.906926 | O76: 20.82 | P76: 3.461 | Q76: =K76-P76 -> 3.249 | R76: 79.43 | S76: =(O76*T76) -> 68.706 | T76: 3.3 | U76: 1738.99 | Y76: 1968.77
A77: 76 | B77: 39965 | C77: 4432596 | D77: =C77/E77 -> 92829.236 | E77: 47.75 | F77: =(D77/100000) -> 0.92829236 | G77: =(F77/'Yearly GDP'!$B$8)*100 -> 77.357696 | H77: =(K77/I77) -> 1.4004961 | I77: =(J77/L77)*100 -> 5.0075113 | J77: =L77/O77 -> 214.87732 | K77: 7.013 | L77: 4291.1 | M77: 3.56 | N77: =K77-I77 -> 2.0054887 | O77: 19.97 | P77: 3.537 | Q77: =K77-P77 -> 3.476 | R77: 80.425 | S77: =(O77*T77) -> 66.8995 | T77: 3.35 | U77: 1735.55 | Y77: 1902.39
A78: 77 | B78: 39995 | C78: 4816459 | D78: =C78/E78 -> 100710.07 | E78: 47.825 | F78: =(D78/100000) -> 1.0071007 | G78: =(F78/'Yearly GDP'!$B$8)*100 -> 83.925057 | H78: =(K78/I78) -> 1.4471864 | I78: =(J78/L78)*100 -> 4.8355899 | J78: =L78/O78 -> 224.19971 | K78: 6.998 | L78: 4636.45 | M78: 3.73 | N78: =K78-I78 -> 2.1624101 | O78: 20.68 | P78: 3.482 | Q78: =K78-P78 -> 3.516 | R78: 78.45 | S78: =(O78*T78) -> 67.21 | T78: 3.25 | U78: 1890.68 | Y78: 2060.84
A79: 78 | B79: 40026 | C79: 4975800 | D79: =C79/E79 -> 102193.47 | E79: 48.69 | F79: =(D79/100000) -> 1.0219347 | G79: =(F79/'Yearly GDP'!$B$8)*100 -> 85.161224 | H79: =(K79/I79) -> 1.5566796 | I79: =(J79/L79)*100 -> 4.7755492 | J79: =L79/O79 -> 222.64088 | K79: 7.434 | L79: 4662.1 | M79: 3.66 | N79: =K79-I79 -> 2.6584508 | O79: 20.94 | P79: 3.401 | Q79: =K79-P79 -> 4.033 | R79: 78.22 | S79: =(O79*T79) -> 71.8242 | T79: 3.43 | U79: 1999.23 | Y79: 2276.27
A80: 79 | B80: 40057 | C80: 5353880 | D80: =C80/E80 -> 112158.37 | E80: 47.735 | F80: =(D80/100000) -> 1.1215837 | G80: =(F80/'Yearly GDP'!$B$8)*100 -> 93.465312 | H80: =(K80/I80) -> 1.652235 | I80: =(J80/L80)*100 -> 4.3668122 | J80: =L80/O80 -> 222.00655 | K80: 7.215 | L80: 5083.95 | M80: 3.76 | N80: =K80-I80 -> 2.8481878 | O80: 22.9 | P80: 3.305 | Q80: =K80-P80 -> 3.91 | R80: 76.86 | S80: =(O80*T80) -> 75.57 | T80: 3.3 | U80: 2167.92 | Y80: 2411.07
A81: 80 | B81: 40087 | C81: 5024830 | D81: =C81/E81 -> 107082.15 | E81: 46.925 | F81: =(D81/100000) -> 1.0708215 | G81: =(F81/'Yearly GDP'!$B$8)*100 -> 89.235127 | H81: =(K81/I81) -> 1.494077 | I81: =(J81/L81)*100 -> 4.8899756 | J81: =L81/O81 -> 230.40098 | K81: 7.306 | L81: 4711.7 | M81: 3.53 | N81: =K81-I81 -> 2.4160244 | O81: 20.45 | P81: 3.388 | Q81: =K81-P81 -> 3.918 | R81: 76.475 | S81: =(O81*T81) -> 66.258 | T81: 3.24 | U81: 2045.06 | Y81: 2245.04
A82: 81 | B82: 40118 | C82: 5430088 | D82: =C82/E82 -> 116688.26 | E82: 46.535 | F82: =(D82/100000) -> 1.1668826 | G82: =(F82/'Yearly GDP'!$B$8)*100 -> 97.240213 | H82: =(K82/I82) -> 1.6233909 | I82: =(J82/L82)*100 -> 4.4702727 | J82: =L82/O82 -> 224.97541 | K82: 7.257 | L82: 5032.7 | M82: 3.56 | N82: =K82-I82 -> 2.7867273 | O82: 22.37 | P82: 3.198 | Q82: =K82-P82 -> 4.059 | R82: 74.935 | S82: =(O82*T82) -> 74.73817 | T82: 3.341 | U82: 2207.61 | Y82: 2379.16
A83: 82 | B83: 40148 | C83: 5699637 | D83: =C83/E83 -> 122810.54 | E83: 46.41 | F83: =(D83/100000) -> 1.2281054 | G83: =(F83/'Yearly GDP'!$B$8)*100 -> 102.34211 | H83: =(K83/I83) -> 1.7792243 | I83: =(J83/L83)*100 -> 4.3159258 | J83: =L83/O83 -> 224.47346 | K83: 7.679 | L83: 5201.05 | M83: 3.65 | N83: =K83-I83 -> 3.3630742 | O83: 23.17 | P83: 3.837 | Q83: =K83-P83 -> 3.842 | R83: 78.22 | S83: =(O83*T83) -> 84.5705 | T83: 3.65 | U83: 2298.2 | Y83: 2598.13
A84: 83 | B84: 40179 | C84: 5782965 | D84: =C84/E84 -> 125375.93 | E84: 46.125 | F84: =(D84/100000) -> 1.2537593 | G84: =(F84/'Yearly GDP'!$B$9)*100 -> 93.564131 | H84: =(K84/I84) -> 1.59411 | I84: =(J84/L84)*100 -> 4.7619048 | J84: =L84/O84 -> 232.47857 | K84: 7.591 | L84: 4882.05 | M84: 3.43 | N84: =K84-I84 -> 2.8290952 | O84: 21 | P84: 3.588 | Q84: =K84-P84 -> 4.003 | R84: 79.65 | S84: =(O84*T84) -> 83.538 | T84: 3.978 | U84: 2275.27 | Y84: 2581.02
A85: 84 | B85: 40210 | C85: 5755305 | D85: =C85/E85 -> 124830.39 | E85: 46.105 | F85: =(D85/100000) -> 1.2483039 | G85: =(F85/'Yearly GDP'!$B$9)*100 -> 93.157005 | H85: =(K85/I85) -> 1.6451488 | I85: =(J85/L85)*100 -> 4.7801147 | J85: =L85/O85 -> 235.29159 | K85: 7.864 | L85: 4922.3 | M85: 3.46 | N85: =K85-I85 -> 3.0838853 | O85: 20.92 | P85: 3.619 | Q85: =K85-P85 -> 4.245 | R85: 80.44 | S85: =(O85*T85) -> 86.818 | T85: 4.15 | U85: 2233.48 | Y85: 2514.07
A86: 85 | B86: 40238 | C86: 6009173 | D86: =C86/E86 -> 134058.52 | E86: 44.825 | F86: =(D86/100000) -> 1.3405852 | G86: =(F86/'Yearly GDP'!$B$9)*100 -> 100.04367 | H86: =(K86/I86) -> 1.752905 | I86: =(J86/L86)*100 -> 4.4782803 | J86: =L86/O86 -> 235.06941 | K86: 7.85 | L86: 5249.1 | M86: 3.7 | N86: =K86-I86 -> 3.3717197 | O86: 22.33 | P86: 3.833 | Q86: =K86-P86 -> 4.017 | R86: 81.291 | S86: =(O86*T86) -> 94.9025 | T86: 4.25 | U86: 2375.38 | Y86: 2657.38
A87: 86 | B87: 40269 | C87: 6117858 | D87: =C87/E87 -> 138178.61 | E87: 44.275 | F87: =(D87/100000) -> 1.3817861 | G87: =(F87/'Yearly GDP'!$B$9)*100 -> 103.11837 | H87: =(K87/I87) -> 1.7967969 | I87: =(J87/L87)*100 -> 4.4863167 | J87: =L87/O87 -> 236.7878 | K87: 8.061 | L87: 5278 | M87: 3.75 | N87: =K87-I87 -> 3.5746833 | O87: 22.29 | P87: 3.659 | Q87: =K87-P87 -> 4.402 | R87: 81.991 | S87: =(O87*T87) -> 91.389 | T87: 4.1 | U87: 2505.41 | Y87: 2807.52
A88: 87 | B88: 40299 | C88: 5932578 | D88: =C88/E88 -> 127953.8 | E88: 46.365 | F88: =(D88/100000) -> 1.279538 | G88: =(F88/'Yearly GDP'!$B$9)*100 -> 95.487911 | H88: =(K88/I88) -> 1.611132 | I88: =(J88/L88)*100 -> 4.6948357 | J88: =L88/O88 -> 238.79343 | K88: 7.564 | L88: 5086.3 | M88: 3.61 | N88: =K88-I88 -> 2.8691643 | O88: 21.3 | P88: 3.3 | Q88: =K88-P88 -> 4.264 | R88: 86.67 | S88: =(O88*T88) -> 106.5 | T88: 5 | U88: 2398 | Y88: 2634.36
A89: 88 | B89: 40330 | C89: 6229136 | D89: =C89/E89 -> 134118.55 | E89: 46.445 | F89: =(D89/100000) -> 1.3411855 | G89: =(F89/'Yearly GDP'!$B$9)*100 -> 100.08847 | H89: =(K89/I89) -> 1.6823225 | I89: =(J89/L89)*100 -> 4.494382 | J89: =L89/O89 -> 238.76404 | K89: 7.561 | L89: 5312.5 | M89: 3.78 | N89: =K89-I89 -> 3.066618 | O89: 22.25 | P89: 2.935 | Q89: =K89-P89 -> 4.626 | R89: 86.281 | S89: =(O89*T89) -> 119.0375 | T89: 5.35 | U89: 2513.14 | Y89: 2787.13
A90: 89 | B90: 40360 | C90: 6340120 | D90: 136625.79 | E90: 46.405 | F90: 1.3662579 | G90: 101.95955 | H90: 1.7408493 | I90: 4.4822949 | J90: 240.59166 | K90: 7.803 | L90: 5367.6 | M90: 3.78 | N90: 3.3207051 | O90: 22.31 | P90: 2.905 | Q90: 4.898 | R90: 81.655 | S90: 129.398 | T90: 5.8 | U90: 2604.85 | Y90: 2854.86
A91: 90 | B91: 40391 | C91: 6393418 | D91: 135842.3 | E91: 47.065 | F91: 1.358423 | G91: 101.37485 | H91: 1.8038528 | I91: 4.3994721 | J91: 237.67708 | K91: 7.936 | L91: 5402.4 | M91: 3.54 | N91: 3.5365279 | O91: 22.73 | P91: 2.47 | Q91: 5.466 | R91: 83.254 | S91: 138.653 | T91: 6.1 | U91: 2675.4 | Y91: 2937.1
A92: 91 | B92: 40422 | C92: 6958533 | D92: 156125.94 | E92: 44.57 | F92: 1.5612594 | G92: 116.51189 | H92: 1.9991192 | I92: 3.9277298 | J92: 236.84014 | K92: 7.852 | L92: 6029.95 | M92: 3.82 | N92: 3.9242702 | O92: 25.46 | P92: 2.512 | Q92: 5.34 | R92: 78.938 | S92: 160.398 | T92: 6.3 | U92: 2832.69 | Y92: 3137.3
A93: 92 | B93: 40452 | C93: 7055094 | D93: 159167.38 | E93: 44.325 | F93: 1.5916738 | G93: 118.78162 | H93: 2.0066991 | I93: 4.0469446 | J93: 243.53298 | K93: 8.121 | L93: 6017.7 | M93: 3.78 | N93: 4.0740554 | O93: 24.71 | P93: 2.603 | Q93: 5.518 | R93: 77.457 | S93: 169.2635 | T93: 6.85 | U93: 2908.54 | Y93: 3249.48
A94: 93 | B94: 40483 | C94: 6894912 | D94: 150543.93 | E94: 45.8 | F94: 1.5054393 | G94: 112.34622 | H94: 1.8866374 | I94: 4.2753313 | J94: 250.64985 | K94: 8.066 | L94: 5862.7 | M94: 3.69 | N94: 3.7906687 | O94: 23.39 | P94: 2.797 | Q94: 5.269 | R94: 81.271 | S94: 161.391 | T94: 6.9 | U94: 2727.2 | Y94: 2957.64
A95: 94 | B95: 40513 | C95: 7139310 | D95: 159669.67 | E95: 44.713 | F95: 1.5966967 | G95: 119.15647 | H95: 1.9371024 | I95: 4.0849673 | J95: 250.59232 | K95: 7.913 | L95: 6134.5 | M95: 3.87 | N95: 3.8280327 | O95: 24.48 | P95: 3.288 | Q95: 4.625 | R95: 79.288 | S95: 176.256 | T95: 7.2 | U95: 2723.32 | Y95: 3020.41
A96: 95 | B96: 40544 | C96: 6441491 | D96: 140567.18 | E96: 45.825 | F96: 1.4056718 | G96: 83.67094 | H96: 1.7159688 | I96: 4.7483381 | J96: 261.43875 | K96: 8.148 | L96: 5505.9 | M96: 3.47 | N96: 3.3996619 | O96: 21.06 | P96: 3.374 | Q96: 4.774 | R96: 77.865 | S96: 151.632 | T96: 7.2 | U96: 2408.75 | Y96: 2650.71
A97: 96 | B97: 40575 | C97: 6195967 | D97: 136882.07 | E97: 45.265 | F97: 1.3688207 | G97: 81.477424 | H97: 1.6319664 | I97: 4.8971596 | J97: 261.17777 | K97: 7.992 | L97: 5333.25 | M97: 3.38 | N97: 3.0948404 | O97: 20.42 | P97: 3.422 | Q97: 4.57 | R97: 76.921 | S97: 146.003 | T97: 7.15 | U97: 2245.85 | Y97: 2489
A98: 97 | B98: 40603 | C98: 6702616 | D98: 150502.21 | E98: 44.535 | F98: 1.5050221 | G98: 89.58465 | H98: 1.767879 | I98: 4.5167118 | J98: 263.49368 | K98: 7.985 | L98: 5833.75 | M98: 3.7 | N98: 3.4682882 | O98: 22.14 | P98: 3.47 | Q98: 4.515 | R98: 76.072 | S98: 160.515 | T98: 7.25 | U98: 2457.29 | Y98: 2649.12
A99: 98 | B99: 40634 | C99: 6753614 | D99: 152606.8 | E99: 44.255 | F99: 1.526068 | G99: 90.837382 | H99: 1.737636 | I99: 4.6816479 | J99: 269.17135 | K99: 8.135 | L99: 5749.5 | M99: 3.65 | N99: 3.4533521 | O99: 21.36 | P99: 3.29 | Q99: 4.845 | R99: 73.107 | S99: 162.336 | T99: 7.6 | U99: 2509.49 | Y99: 2769.75
A100: 99 | B100: 40664 | C100: 6569743 | D100: 145799.89 | E100: 45.06 | F100: 1.4579989 | G100: 86.785648 | H100: 1.7267783 | I100: 4.8709206 | J100: 270.83049 | K100: 8.411 | L100: 5560.15 | M100: 3.45 | N100: 3.5400794 | O100: 20.53 | P100: 3.059 | Q100: 5.352 | R100: 74.696 | S100: 168.346 | T100: 8.2 | U100: 2458.62 | Y100: 2678.73
...

Sheet Daily
A1: S.no | B1: Date | C1: Market Cap | D1: US $ | E1: USD/INR | F1: Trillion | G1: Market Cap to GDP | H1: BEER | I1: Nifty 50 Earning Yield | J1: NIFTY 50 EPS | K1: India 10Yr Yield | L1: Nifty 50 | M1: Price to Book | N1: Equity Earnings Yield vs 10 Year G Sec Yield Gap | O1: Nifty 50 pe | P1: US 10yr Bond | Q1: India yr- US 10yr | R1: Dollar index | S1: PREITY Ratio | T1: 91 day T Bill | U1: Nifty Midcap 150 | V1: Midcap 150 PE | W1: Midcap EPS | X1: Midcap Earning Yield | Y1: Nifty Smallcap 250 | Z1: Smallcap 250 PE | AA1: Smallcap EPS | AB1: Smallcap Earning Yield
A2: 1 | B2: 37683 | C2: 582058 | D2: =C2/E2 -> 12220.407 | E2: 47.63 | F2: =(D2/100000) -> 0.12220407 | G2: =(F2/'Yearly GDP'!$B$2)*100 -> 23.731711 | H2: =(K2/I2) -> 0.878114 | I2: =(J2/L2)*100 -> 6.9637883 | J2: =L2/O2 -> 73.736072 | K2: 6.115 | L2: 1058.85 | M2: 2.32 | N2: =K2-I2 -> -0.8487883 | O2: 14.36 | P2: 3.675 | Q2: =K2-P2 -> 2.44 | R2: 99.18 | S2: =(O2*T2) -> 77.544 | T2: 5.4
A3: 2 | B3: 37684 | C3: 575406 | D3: =C3/E3 -> 12075.677 | E3: 47.65 | F3: =(D3/100000) -> 0.12075677 | G3: =(F3/'Yearly GDP'!$B$2)*100 -> 23.450648 | H3: =(K3/I3) -> 0.883592 | I3: =(J3/L3)*100 -> 7.0224719 | J3: =L3/O3 -> 73.497191 | K3: 6.205 | L3: 1046.6 | M3: 2.3 | N3: =K3-I3 -> -0.81747191 | O3: 14.24 | P3: 3.648 | Q3: =K3-P3 -> 2.557 | R3: 99.16 | S3: =(O3*T3) -> 75.472 | T3: 5.3
A4: 3 | B4: 37685 | C4: 571902 | D4: =C4/E4 -> 12002.141 | E4: 47.65 | F4: =(D4/100000) -> 0.12002141 | G4: =(F4/'Yearly GDP'!$B$2)*100 -> 23.307843 | H4: =(K4/I4) -> 0.8908056 | I4: =(J4/L4)*100 -> 7.0621469 | J4: =L4/O4 -> 73.495763 | K4: 6.291 | L4: 1040.7 | M4: 2.28 | N4: =K4-I4 -> -0.77114689 | O4: 14.16 | P4: 3.631 | Q4: =K4-P4 -> 2.66 | R4: 98.29 | S4: =(O4*T4) -> 76.464 | T4: 5.4
A5: 4 | B5: 37686 | C5: 567021 | D5: =C5/E5 -> 11917.213 | E5: 47.58 | F5: =(D5/100000) -> 0.11917213 | G5: =(F5/'Yearly GDP'!$B$2)*100 -> 23.142916 | H5: =(K5/I5) -> 0.8756123 | I5: =(J5/L5)*100 -> 7.1275837 | J5: =L5/O5 -> 73.503207 | K5: 6.241 | L5: 1031.25 | M5: 2.26 | N5: =K5-I5 -> -0.88658375 | O5: 14.03 | P5: 3.654 | Q5: =K5-P5 -> 2.587 | R5: 98.37 | S5: =(O5*T5) -> 76.4635 | T5: 5.45
A6: 5 | B6: 37687 | C6: 558089 | D6: =C6/E6 -> 11712.256 | E6: 47.65 | F6: =(D6/100000) -> 0.11712256 | G6: =(F6/'Yearly GDP'!$B$2)*100 -> 22.744895 | H6: =(K6/I6) -> 0.88922 | I6: =(J6/L6)*100 -> 7.2254335 | J6: =L6/O6 -> 73.489884 | K6: 6.425 | L6: 1017.1 | M6: 2.23 | N6: =K6-I6 -> -0.80043353 | O6: 13.84 | P6: 3.644 | Q6: =K6-P6 -> 2.781 | R6: 98.1 | S6: =(O6*T6) -> 78.196 | T6: 5.65
A7: 6 | B7: 37690 | C7: 552012.05 | D7: =C7/E7 -> 11584.723 | E7: 47.65 | F7: =(D7/100000) -> 0.11584723 | G7: =(F7/'Yearly GDP'!$B$2)*100 -> 22.497229 | H7: =(K7/I7) -> 0.887623 | I7: =(J7/L7)*100 -> 7.2992701 | J7: =L7/O7 -> 73.481752 | K7: 6.479 | L7: 1006.7 | M7: 2.21 | N7: =K7-I7 -> -0.82027007 | O7: 13.7 | P7: 3.564 | Q7: =K7-P7 -> 2.915 | R7: 97.92 | S7: =(O7*T7) -> 78.09 | T7: 5.7
A8: 7 | B8: 37691 | C8: 555359 | D8: =C8/E8 -> 11669.657 | E8: 47.59 | F8: =(D8/100000) -> 0.11669657 | G8: =(F8/'Yearly GDP'!$B$2)*100 -> 22.662169 | H8: =(K8/I8) -> 0.8857734 | I8: =(J8/L8)*100 -> 7.2411296 | J8: =L8/O8 -> 73.464881 | K8: 6.414 | L8: 1014.55 | M8: 2.23 | N8: =K8-I8 -> -0.82712962 | O8: 13.81 | P8: 3.582 | Q8: =K8-P8 -> 2.832 | R8: 98.08 | S8: =(O8*T8) -> 78.717 | T8: 5.7
A9: 8 | B9: 37692 | C9: 551150 | D9: =C9/E9 -> 11578.782 | E9: 47.6 | F9: =(D9/100000) -> 0.11578782 | G9: =(F9/'Yearly GDP'!$B$2)*100 -> 22.485691 | H9: =(K9/I9) -> 0.8671406 | I9: =(J9/L9)*100 -> 7.3367572 | J9: =L9/O9 -> 73.492296 | K9: 6.362 | L9: 1001.7 | M9: 2.2 | N9: =K9-I9 -> -0.97475715 | O9: 13.63 | P9: 3.586 | Q9: =K9-P9 -> 2.776 | R9: 98.19 | S9: =(O9*T9) -> 80.417 | T9: 5.9
A10: 9 | B10: 37693 | C10: 549801 | D10: =C10/E10 -> 11548.015 | E10: 47.61 | F10: =(D10/100000) -> 0.11548015 | G10: =(F10/'Yearly GDP'!$B$2)*100 -> 22.425943 | H10: =(K10/I10) -> 0.866728 | I10: =(J10/L10)*100 -> 7.3529412 | J10: =L10/O10 -> 73.503676 | K10: 6.373 | L10: 999.65 | M10: 2.19 | N10: =K10-I10 -> -0.97994118 | O10: 13.6 | P10: 3.75 | Q10: =K10-P10 -> 2.623 | R10: 99.61 | S10: =(O10*T10) -> 78.88 | T10: 5.8
A11: 10 | B11: 37697 | C11: 546264 | D11: =C11/E11 -> 11468.906 | E11: 47.63 | F11: =(D11/100000) -> 0.11468906 | G11: =(F11/'Yearly GDP'!$B$2)*100 -> 22.272316 | H11: =(K11/I11) -> 0.8732864 | I11: =(J11/L11)*100 -> 7.4019245 | J11: =L11/O11 -> 73.50111 | K11: 6.464 | L11: 993 | M11: 2.18 | N11: =K11-I11 -> -0.9379245 | O11: 13.51 | P11: 3.84 | Q11: =K11-P11 -> 2.624 | R11: 99.69 | S11: =(O11*T11) -> 77.007 | T11: 5.7
A12: 11 | B12: 37699 | C12: 549929 | D12: =C12/E12 -> 11541.007 | E12: 47.65 | F12: =(D12/100000) -> 0.11541007 | G12: =(F12/'Yearly GDP'!$B$2)*100 -> 22.412334 | H12: =(K12/I12) -> 0.8852547 | I12: =(J12/L12)*100 -> 7.293946 | J12: =L12/O12 -> 73.223924 | K12: 6.457 | L12: 1003.9 | M12: 2.2 | N12: =K12-I12 -> -0.83694602 | O12: 13.71 | P12: 3.986 | Q12: =K12-P12 -> 2.471 | R12: 102.11 | S12: =(O12*T12) -> 80.2035 | T12: 5.85
A13: 12 | B13: 37700 | C13: 558210 | D13: =C13/E13 -> 11702.516 | E13: 47.7 | F13: =(D13/100000) -> 0.11702516 | G13: =(F13/'Yearly GDP'!$B$2)*100 -> 22.725979 | H13: =(K13/I13) -> 0.903 | I13: =(J13/L13)*100 -> 7.1428571 | J13: =L13/O13 -> 73.232143 | K13: 6.45 | L13: 1025.25 | M13: 2.25 | N13: =K13-I13 -> -0.69285714 | O13: 14 | P13: 3.955 | Q13: =K13-P13 -> 2.495 | R13: 101.63 | S13: =(O13*T13) -> 81.9 | T13: 5.85
... A212: 211 | B212: 37986 | C212: 1167029 | D212: =C212/E212 -> 25578.718 | E212: 45.625 | F212: =(D212/100000) -> 0.25578718 | G212: =(F212/'Yearly GDP'!$B$2)*100 -> 49.6732 | H212: =(K212/I212) -> 1.0617906 | I212: =(J212/L212)*100 -> 4.8239267 | J212: =L212/O212 -> 90.677762 | K212: 5.122 | L212: 1879.75 | M212: 4.05 | N212: =K212-I212 -> 0.29807332 | O212: 20.73 | P212: 4.253 | Q212: =K212-P212 -> 0.869 | R212: 87.26 | S212: =(O212*T212) -> 87.8952 | T212: 4.24
A213: 212 | B213: 37987 | C213: 1190885 | D213: =C213/E213 -> 26118.19 | E213: 45.596 | F213: =(D213/100000) -> 0.2611819 | G213: =(F213/'Yearly GDP'!$B$3)*100 -> 42.978756 | H213: =(K213/I213) -> 1.0812843 | I213: =(J213/L213)*100 -> 4.7415837 | J213: =L213/O213 -> 90.670934 | K213: 5.127 | L213: 1912.25 | M213: 4.12 | N213: =K213-I213 -> 0.38541631 | O213: 21.09 | P213: 4.253 | Q213: =K213-P213 -> 0.874 | R213: 87.26 | S213: =(O213*T213) -> 88.7889 | T213: 4.21
A214: 213 | B214: 37988 | C214: 1225500 | D214: =C214/E214 -> 26851.446 | E214: 45.64 | F214: =(D214/100000) -> 0.26851446 | G214: =(F214/'Yearly GDP'!$B$3)*100 -> 44.185365 | H214: =(K214/I214) -> 1.0989666 | I214: =(J214/L214)*100 -> 4.6598322 | J214: =L214/O214 -> 90.682665 | K214: 5.121 | L214: 1946.05 | M214: 4.19 | N214: =K214-I214 -> 0.46116775 | O214: 21.46 | P214: 4.374 | Q214: =K214-P214 -> 0.747 | R214: 86.93 | S214: =(O214*T214) -> 90.5612 | T214: 4.22
A215: 214 | B215: 37991 | C215: 1230103 | D215: =C215/E215 -> 26981.86 | E215: 45.59 | F215: =(D215/100000) -> 0.2698186 | G215: =(F215/'Yearly GDP'!$B$3)*100 -> 44.399967 | H215: =(K215/I215) -> 1.103872 | I215: =(J215/L215)*100 -> 4.6382189 | J215: =L215/O215 -> 90.67718 | K215: 5.12 | L215: 1955 | M215: 4.21 | N215: =K215-I215 -> 0.48178108 | O215: 21.56 | P215: 4.38 | Q215: =K215-P215 -> 0.74 | R215: 86.35 | S215: =(O215*T215) -> 89.6896 | T215: 4.16
A216: 215 | B216: 37992 | C216: 1207632 | D216: =C216/E216 -> 26474.449 | E216: 45.615 | F216: =(D216/100000) -> 0.26474449 | G216: =(F216/'Yearly GDP'!$B$3)*100 -> 43.564998 | H216: =(K216/I216) -> 1.08715 | I216: =(J216/L216)*100 -> 4.7058824 | J216: =L216/O216 -> 90.668235 | K216: 5.116 | L216: 1926.7 | M216: 4.15 | N216: =K216-I216 -> 0.41011765 | O216: 21.25 | P216: 4.274 | Q216: =K216-P216 -> 0.842 | R216: 85.93 | S216: =(O216*T216) -> 88.4 | T216: 4.16
A217: 216 | B217: 37993 | C217: 1201998 | D217: =C217/E217 -> 26397.233 | E217: 45.535 | F217: =(D217/100000) -> 0.26397233 | G217: =(F217/'Yearly GDP'!$B$3)*100 -> 43.437935 | H217: =(K217/I217) -> 1.0821566 | I217: =(J217/L217)*100 -> 4.730369 | J217: =L217/O217 -> 90.669347 | K217: 5.119 | L217: 1916.75 | M217: 4.12 | N217: =K217-I217 -> 0.38863103 | O217: 21.14 | P217: 4.245 | Q217: =K217-P217 -> 0.874 | R217: 86.52 | S217: =(O217*T217) -> 89.6336 | T217: 4.24
A218: 217 | B218: 37994 | C218: 1242777 | D218: =C218/E218 -> 27310.779 | E218: 45.505 | F218: =(D218/100000) -> 0.27310779 | G218: =(F218/'Yearly GDP'!$B$3)*100 -> 44.941219 | H218: =(K218/I218) -> 1.1100323 | I218: =(J218/L218)*100 -> 4.6061723 | J218: =L218/O218 -> 90.674804 | K218: 5.113 | L218: 1968.55 | M218: 4.24 | N218: =K218-I218 -> 0.50682773 | O218: 21.71 | P218: 4.269 | Q218: =K218-P218 -> 0.844 | R218: 85.88 | S218: =(O218*T218) -> 91.6162 | T218: 4.22
A219: 218 | B219: 37995 | C219: 1241569 | D219: =C219/E219 -> 27329.276 | E219: 45.43 | F219: =(D219/100000) -> 0.27329276 | G219: =(F219/'Yearly GDP'!$B$3)*100 -> 44.971657 | H219: =(K219/I219) -> 1.113165 | I219: =(J219/L219)*100 -> 4.5977011 | J219: =L219/O219 -> 90.662069 | K219: 5.118 | L219: 1971.9 | M219: 4.24 | N219: =K219-I219 -> 0.52029885 | O219: 21.75 | P219: 4.084 | Q219: =K219-P219 -> 1.034 | R219: 85.39 | S219: =(O219*T219) -> 91.785 | T219: 4.22
A220: 219 | B220: 37998 | C220: 1222453 | D220: =C220/E220 -> 26944.082 | E220: 45.37 | F220: =(D220/100000) -> 0.26944082 | G220: =(F220/'Yearly GDP'!$B$3)*100 -> 44.337802 | H220: =(K220/I220) -> 1.103044 | I220: =(J220/L220)*100 -> 4.6598322 | J220: =L220/O220 -> 90.661696 | K220: 5.14 | L220: 1945.6 | M220: 4.19 | N220: =K220-I220 -> 0.48016775 | O220: 21.46 | P220: 4.09 | Q220: =K220-P220 -> 1.05 | R220: 85.86 | S220: =(O220*T220) -> 90.7758 | T220: 4.23
A221: 220 | B221: 37999 | C221: 1225212 | D221: =C221/E221 -> 27016.803 | E221: 45.35 | F221: =(D221/100000) -> 0.27016803 | G221: =(F221/'Yearly GDP'!$B$3)*100 -> 44.457467 | H221: =(K221/I221) -> 1.1107248 | I221: =(J221/L221)*100 -> 4.6168052 | J221: =L221/O221 -> 90.655586 | K221: 5.128 | L221: 1963.6 | M221: 4.23 | N221: =K221-I221 -> 0.51119483 | O221: 21.66 | P221: 4.015 | Q221: =K221-P221 -> 1.113 | R221: 85.78 | S221: =(O221*T221) -> 91.4052 | T221: 4.22
A222: 221 | B222: 38000 | C222: 1235165.1 | D222: =C222/E222 -> 27224.269 | E222: 45.37 | F222: =(D222/100000) -> 0.27224269 | G222: =(F222/'Yearly GDP'!$B$3)*100 -> 44.798863 | H222: =(K222/I222) -> 1.1201064 | I222: =(J222/L222)*100 -> 4.5745654 | J222: =L222/O222 -> 90.674748 | K222: 5.124 | L222: 1982.15 | M222: 4.27 | N222: =K222-I222 -> 0.54943458 | O222: 21.86 | P222: 3.996 | Q222: =K222-P222 -> 1.128 | R222: 86.32 | S222: =(O222*T222) -> 92.6864 | T222: 4.24
A223: 222 | B223: 38001 | C223: 1218834 | D223: =C223/E223 -> 26828.836 | E223: 45.43 | F223: =(D223/100000) -> 0.26828836 | G223: =(F223/'Yearly GDP'!$B$3)*100 -> 44.148158 | H223: =(K223/I223) -> 1.1018016 | I223: =(J223/L223)*100 -> 4.6641791 | J223: =L223/O223 -> 90.692631 | K223: 5.139 | L223: 1944.45 | M223: 4.18 | N223: =K223-I223 -> 0.4748209 | O223: 21.44 | P223: 3.974 | Q223: =K223-P223 -> 1.165 | R223: 86.87 | S223: =(O223*T223) -> 91.3344 | T223: 4.26
A224: 223 | B224: 38002 | C224: 1187137 | D224: =C224/E224 -> 26148.392 | E224: 45.4 | F224: =(D224/100000) -> 0.26148392 | G224: =(F224/'Yearly GDP'!$B$3)*100 -> 43.028455 | H224: =(K224/I224) -> 1.0769248 | I224: =(J224/L224)*100 -> 4.7709924 | J224: =L224/O224 -> 90.679866 | K224: 5.138 | L224: 1900.65 | M224: 4.09 | N224: =K224-I224 -> 0.36700763 | O224: 20.96 | P224: 4.029 | Q224: =K224-P224 -> 1.109 | R224: 88.05 | S224: =(O224*T224) -> 88.6608 | T224: 4.23
... A464: 463 | B464: 38352 | C464: 1579161 | D464: =C464/E464 -> 36512.393 | E464: 43.25 | F464: =(D464/100000) -> 0.36512393 | G464: =(F464/'Yearly GDP'!$B$3)*100 -> 60.082924 | H464: =(K464/I464) -> 1.0273592 | I464: =(J464/L464)*100 -> 6.5274151 | J464: =L464/O464 -> 135.80287 | K464: 6.706 | L464: 2080.5 | M464: 3.61 | N464: =K464-I464 -> 0.17858486 | O464: 15.32 | P464: 4.222 | Q464: =K464-P464 -> 2.484 | R464: 81 | S464: =(O464*T464) -> 81.196 | T464: 5.3
A465: 464 | B465: 38355 | C465: 1605364 | D465: =C465/E465 -> 36989.954 | E465: 43.4 | F465: =(D465/100000) -> 0.36989954 | G465: =(F465/'Yearly GDP'!$B$4)*100 -> 52.160973 | H465: =(K465/I465) -> 1.0179666 | I465: =(J465/L465)*100 -> 6.4226076 | J465: =L465/O465 -> 135.83815 | K465: 6.538 | L465: 2115 | M465: 3.67 | N465: =K465-I465 -> 0.11539242 | O465: 15.57 | P465: 4.216 | Q465: =K465-P465 -> 2.322 | R465: 81.41 | S465: =(O465*T465) -> 79.407 | T465: 5.1
A466: 465 | B466: 38356 | C466: 1603244 | D466: =C466/E466 -> 36860.421 | E466: 43.495 | F466: =(D466/100000) -> 0.36860421 | G466: =(F466/'Yearly GDP'!$B$4)*100 -> 51.978313 | H466: =(K466/I466) -> 1.0045265 | I466: =(J466/L466)*100 -> 6.4557779 | J466: =L466/O466 -> 135.81343 | K466: 6.485 | L466: 2103.75 | M466: 3.65 | N466: =K466-I466 -> 0.029222079 | O466: 15.49 | P466: 4.295 | Q466: =K466-P466 -> 2.19 | R466: 82.7 | S466: =(O466*T466) -> 78.999 | T466: 5.1
A467: 466 | B467: 38357 | C467: 1548506.1 | D467: =C467/E467 -> 35573.308 | E467: 43.53 | F467: =(D467/100000) -> 0.35573308 | G467: =(F467/'Yearly GDP'!$B$4)*100 -> 50.163305 | H467: =(K467/I467) -> 0.9824232 | I467: =(J467/L467)*100 -> 6.684492 | J467: =L467/O467 -> 135.84225 | K467: 6.567 | L467: 2032.2 | M467: 3.52 | N467: =K467-I467 -> -0.11749198 | O467: 14.96 | P467: 4.287 | Q467: =K467-P467 -> 2.28 | R467: 82.65 | S467: =(O467*T467) -> 77.792 | T467: 5.2
A468: 467 | B468: 38358 | C468: 1523410.1 | D468: =C468/E468 -> 34721.598 | E468: 43.875 | F468: =(D468/100000) -> 0.34721598 | G468: =(F468/'Yearly GDP'!$B$4)*100 -> 48.962276 | H468: =(K468/I468) -> 0.9715955 | I468: =(J468/L468)*100 -> 6.7980965 | J468: =L468/O468 -> 135.84976 | K468: 6.605 | L468: 1998.35 | M468: 3.47 | N468: =K468-I468 -> -0.19309653 | O468: 14.71 | P468: 4.263 | Q468: =K468-P468 -> 2.342 | R468: 83.24 | S468: =(O468*T468) -> 75.7565 | T468: 5.15
A469: 468 | B469: 38359 | C469: 1545630.1 | D469: =C469/E469 -> 35328.688 | E469: 43.75 | F469: =(D469/100000) -> 0.35328688 | G469: =(F469/'Yearly GDP'!$B$4)*100 -> 49.818357 | H469: =(K469/I469) -> 0.9717232 | I469: =(J469/L469)*100 -> 6.7385445 | J469: =L469/O469 -> 135.81536 | K469: 6.548 | L469: 2015.5 | M469: 3.49 | N469: =K469-I469 -> -0.19054447 | O469: 14.84 | P469: 4.275 | Q469: =K469-P469 -> 2.273 | R469: 83.72 | S469: =(O469*T469) -> 76.426 | T469: 5.15
A470: 469 | B470: 38362 | C470: 1530226.9 | D470: =C470/E470 -> 34865.047 | E470: 43.89 | F470: =(D470/100000) -> 0.34865047 | G470: =(F470/'Yearly GDP'!$B$4)*100 -> 49.164559 | H470: =(K470/I470) -> 0.9605304 | I470: =(J470/L470)*100 -> 6.8587106 | J470: =L470/O470 -> 135.93964 | K470: 6.588 | L470: 1982 | M470: 3.44 | N470: =K470-I470 -> -0.27071056 | O470: 14.58 | P470: 4.273 | Q470: =K470-P470 -> 2.315 | R470: 83.36 | S470: =(O470*T470) -> 75.816 | T470: 5.2
A471: 470 | B471: 38363 | C471: 1502001 | D471: =C471/E471 -> 34351.081 | E471: 43.725 | F471: =(D471/100000) -> 0.34351081 | G471: =(F471/'Yearly GDP'!$B$4)*100 -> 48.439795 | H471: =(K471/I471) -> 0.9418098 | I471: =(J471/L471)*100 -> 6.9589422 | J471: =L471/O471 -> 135.84203 | K471: 6.554 | L471: 1952.05 | M471: 3.39 | N471: =K471-I471 -> -0.40494224 | O471: 14.37 | P471: 4.244 | Q471: =K471-P471 -> 2.31 | R471: 83.07 | S471: =(O471*T471) -> 79.035 | T471: 5.5
A472: 471 | B472: 38364 | C472: 1462287 | D472: =C472/E472 -> 33569.49 | E472: 43.56 | F472: =(D472/100000) -> 0.3356949 | G472: =(F472/'Yearly GDP'!$B$4)*100 -> 47.337644 | H472: =(K472/I472) -> 0.9246305 | I472: =(J472/L472)*100 -> 7.1174377 | J472: =L472/O472 -> 136.19929 | K472: 6.581 | L472: 1913.6 | M472: 3.32 | N472: =K472-I472 -> -0.53643772 | O472: 14.05 | P472: 4.238 | Q472: =K472-P472 -> 2.343 | R472: 82.18 | S472: =(O472*T472) -> 74.465 | T472: 5.3
A473: 472 | B473: 38365 | C473: 1497439 | D473: =C473/E473 -> 34419.929 | E473: 43.505 | F473: =(D473/100000) -> 0.34419929 | G473: =(F473/'Yearly GDP'!$B$4)*100 -> 48.53688 | H473: =(K473/I473) -> 0.942221 | I473: =(J473/L473)*100 -> 6.9686411 | J473: =L473/O473 -> 136.20557 | K473: 6.566 | L473: 1954.55 | M473: 3.39 | N473: =K473-I473 -> -0.40264111 | O473: 14.35 | P473: 4.167 | Q473: =K473-P473 -> 2.399 | R473: 82.57 | S473: =(O473*T473) -> 75.6245 | T473: 5.27
A474: 473 | B474: 38366 | C474: 1483272.2 | D474: =C474/E474 -> 34016.104 | E474: 43.605 | F474: =(D474/100000) -> 0.34016104 | G474: =(F474/'Yearly GDP'!$B$4)*100 -> 47.967431 | H474: =(K474/I474) -> 0.9426864 | I474: =(J474/L474)*100 -> 7.0521862 | J474: =L474/O474 -> 136.18477 | K474: 6.648 | L474: 1931.1 | M474: 3.35 | N474: =K474-I474 -> -0.40418618 | O474: 14.18 | P474: 4.22 | Q474: =K474-P474 -> 2.428 | R474: 83.13 | S474: =(O474*T474) -> 74.7286 | T474: 5.27
A475: 474 | B475: 38369 | C475: 1479794.1 | D475: =C475/E475 -> 33940.232 | E475: 43.6 | F475: =(D475/100000) -> 0.33940232 | G475: =(F475/'Yearly GDP'!$B$4)*100 -> 47.860441 | H475: =(K475/I475) -> 0.947973 | I475: =(J475/L475)*100 -> 7.057163 | J475: =L475/O475 -> 136.4079 | K475: 6.69 | L475: 1932.9 | M475: 3.35 | N475: =K475-I475 -> -0.36716302 | O475: 14.17 | P475: 4.22 | Q475: =K475-P475 -> 2.47 | R475: 83.13 | S475: =(O475*T475) -> 75.101 | T475: 5.3
A476: 475 | B476: 38370 | C476: 1483489 | D476: =C476/E476 -> 33954.887 | E476: 43.69 | F476: =(D476/100000) -> 0.33954887 | G476: =(F476/'Yearly GDP'!$B$4)*100 -> 47.881107 | H476: =(K476/I476) -> 0.9531423 | I476: =(J476/L476)*100 -> 7.0472163 | J476: =L476/O476 -> 136.29669 | K476: 6.717 | L476: 1934.05 | M476: 3.36 | N476: =K476-I476 -> -0.33021635 | O476: 14.19 | P476: 4.193 | Q476: =K476-P476 -> 2.524 | R476: 83.46 | S476: =(O476*T476) -> 73.788 | T476: 5.2
... A525: 524 | B525: 38442 | C525: 1585585 | D525: =C525/E525 -> 36304.179 | E525: 43.675 | F525: =(D525/100000) -> 0.36304179 | G525: =(F525/'Yearly GDP'!$B$4)*100 -> 51.193934 | H525: =(K525/I525) -> 0.974696 | I525: =(J525/L525)*100 -> 6.8493151 | J525: =L525/O525 -> 139.42808 | K525: 6.676 | L525: 2035.65 | M525: 3.82 | N525: =K525-I525 -> -0.17331507 | O525: 14.6 | P525: 4.488 | Q525: =K525-P525 -> 2.188 | R525: 84.05 | S525: =(O525*T525) -> 76.65 | T525: 5.25
A526: 525 | B526: 38443 | C526: 1615908 | D526: =C526/E526 -> 36998.466 | E526: 43.675 | F526: =(D526/100000) -> 0.36998466 | G526: =(F526/'Yearly GDP'!$B$4)*100 -> 52.172976 | H526: =(K526/I526) -> 0.9910152 | I526: =(J526/L526)*100 -> 6.7385445 | J526: =L526/O526 -> 139.32951 | K526: 6.678 | L526: 2067.65 | M526: 3.88 | N526: =K526-I526 -> -0.060544474 | O526: 14.84 | P526: 4.451 | Q526: =K526-P526 -> 2.227 | R526: 84.4 | S526: =(O526*T526) -> 78.0584 | T526: 5.26 | U526: 1000 | Y526: 1000
A527: 526 | B527: 38446 | C527: 1614967 | D527: =C527/E527 -> 36913.531 | E527: 43.75 | F527: =(D527/100000) -> 0.36913531 | G527: =(F527/'Yearly GDP'!$B$4)*100 -> 52.053207 | H527: =(K527/I527) -> 0.999675 | I527: =(J527/L527)*100 -> 6.7521945 | J527: =L527/O527 -> 139.32478 | K527: 6.75 | L527: 2063.4 | M527: 3.86 | N527: =K527-I527 -> -0.0021944632 | O527: 14.81 | P527: 4.462 | Q527: =K527-P527 -> 2.288 | R527: 84.78 | S527: =(O527*T527) -> 77.7525 | T527: 5.25 | U527: 1009.3 | Y527: 1007.5
A528: 527 | B528: 38447 | C528: 1603647 | D528: =C528/E528 -> 36646.412 | E528: 43.76 | F528: =(D528/100000) -> 0.36646412 | G528: =(F528/'Yearly GDP'!$B$4)*100 -> 51.676531 | H528: =(K528/I528) -> 0.989983 | I528: =(J528/L528)*100 -> 6.7980965 | J528: =L528/O528 -> 139.53433 | K528: 6.73 | L528: 2052.55 | M528: 3.84 | N528: =K528-I528 -> -0.068096533 | O528: 14.71 | P528: 4.472 | Q528: =K528-P528 -> 2.258 | R528: 84.6 | S528: =(O528*T528) -> 77.2275 | T528: 5.25 | U528: 1002.37 | Y528: 998.77
A529: 528 | B529: 38448 | C529: 1616468 | D529: =C529/E529 -> 36973.193 | E529: 43.72 | F529: =(D529/100000) -> 0.36973193 | G529: =(F529/'Yearly GDP'!$B$4)*100 -> 52.137338 | H529: =(K529/I529) -> 1.0117026 | I529: =(J529/L529)*100 -> 6.7430883 | J529: =L529/O529 -> 139.53473 | K529: 6.822 | L529: 2069.3 | M529: 3.87 | N529: =K529-I529 -> 0.078911666 | O529: 14.83 | P529: 4.426 | Q529: =K529-P529 -> 2.396 | R529: 84.68 | S529: =(O529*T529) -> 77.8575 | T529: 5.25 | U529: 1011.84 | Y529: 1017.08
A530: 529 | B530: 38449 | C530: 1609652 | D530: =C530/E530 -> 36838.357 | E530: 43.695 | F530: =(D530/100000) -> 0.36838357 | G530: =(F530/'Yearly GDP'!$B$4)*100 -> 51.9472 | H530: =(K530/I530) -> 1.0260225 | I530: =(J530/L530)*100 -> 6.7980965 | J530: =L530/O530 -> 139.55472 | K530: 6.975 | L530: 2052.85 | M530: 3.84 | N530: =K530-I530 -> 0.17690347 | O530: 14.71 | P530: 4.488 | Q530: =K530-P530 -> 2.487 | R530: 84.88 | S530: =(O530*T530) -> 77.2275 | T530: 5.25 | U530: 1011.98 | Y530: 1018.96
A531: 530 | B531: 38450 | C531: 1597095 | D531: =C531/E531 -> 36563.53 | E531: 43.68 | F531: =(D531/100000) -> 0.3656353 | G531: =(F531/'Yearly GDP'!$B$4)*100 -> 51.559656 | H531: =(K531/I531) -> 1.021384 | I531: =(J531/L531)*100 -> 6.8681319 | J531: =L531/O531 -> 139.50549 | K531: 7.015 | L531: 2031.2 | M531: 3.8 | N531: =K531-I531 -> 0.14686813 | O531: 14.56 | P531: 4.474 | Q531: =K531-P531 -> 2.541 | R531: 84.41 | S531: =(O531*T531) -> 76.44 | T531: 5.25 | U531: 1005.67 | Y531: 1011.39
A532: 531 | B532: 38453 | C532: 1580500 | D532: =C532/E532 -> 36212.625 | E532: 43.645 | F532: =(D532/100000) -> 0.36212625 | G532: =(F532/'Yearly GDP'!$B$4)*100 -> 51.064831 | H532: =(K532/I532) -> 1.0075878 | I532: =(J532/L532)*100 -> 6.9492703 | J532: =L532/O532 -> 139.55525 | K532: 7.002 | L532: 2008.2 | M532: 3.76 | N532: =K532-I532 -> 0.052729673 | O532: 14.39 | P532: 4.438 | Q532: =K532-P532 -> 2.564 | R532: 84.12 | S532: =(O532*T532) -> 78.1377 | T532: 5.43 | U532: 994.8 | Y532: 1003.75
A533: 532 | B533: 38454 | C533: 1592933 | D533: =C533/E533 -> 36455.727 | E533: 43.695 | F533: =(D533/100000) -> 0.36455727 | G533: =(F533/'Yearly GDP'!$B$4)*100 -> 51.407639 | H533: =(K533/I533) -> 1.025793 | I533: =(J533/L533)*100 -> 6.8259386 | J533: =L533/O533 -> 138.22184 | K533: 7.002 | L533: 2024.95 | M533: 3.82 | N533: =K533-I533 -> 0.17606143 | O533: 14.65 | P533: 4.358 | Q533: =K533-P533 -> 2.644 | R533: 84.4 | S533: =(O533*T533) -> 79.5495 | T533: 5.43 | U533: 1001.82 | Y533: 1011.74
A534: 533 | B534: 38455 | C534: 1593409 | D534: =C534/E534 -> 36437.434 | E534: 43.73 | F534: =(D534/100000) -> 0.36437434 | G534: =(F534/'Yearly GDP'!$B$4)*100 -> 51.381843 | H534: =(K534/I534) -> 1.0166904 | I534: =(J534/L534)*100 -> 6.8870523 | J534: =L534/O534 -> 139.4938 | K534: 7.002 | L534: 2025.45 | M534: 3.79 | N534: =K534-I534 -> 0.11494766 | O534: 14.52 | P534: 4.366 | Q534: =K534-P534 -> 2.636 | R534: 84.4 | S534: =(O534*T534) -> 74.778 | T534: 5.15 | U534: 1003.46 | Y534: 1009.74
A535: 534 | B535: 38457 | C535: 1546977 | D535: =C535/E535 -> 35343.317 | E535: 43.77 | F535: =(D535/100000) -> 0.35343317 | G535: =(F535/'Yearly GDP'!$B$4)*100 -> 49.838987 | H535: =(K535/I535) -> 0.975384 | I535: =(J535/L535)*100 -> 7.1684588 | J535: =L535/O535 -> 140.23656 | K535: 6.992 | L535: 1956.3 | M535: 3.66 | N535: =K535-I535 -> -0.17645878 | O535: 13.95 | P535: 4.247 | Q535: =K535-P535 -> 2.745 | R535: 84.5 | S535: =(O535*T535) -> 72.54 | T535: 5.2 | U535: 980.77 | Y535: 984.13
A536: 535 | B536: 38460 | C536: 1531053.1 | D536: =C536/E536 -> 35039.549 | E536: 43.695 | F536: =(D536/100000) -> 0.35039549 | G536: =(F536/'Yearly GDP'!$B$4)*100 -> 49.410631 | H536: =(K536/I536) -> 0.9614 | I536: =(J536/L536)*100 -> 7.2727273 | J536: =L536/O536 -> 140.20364 | K536: 6.992 | L536: 1927.8 | M536: 3.61 | N536: =K536-I536 -> -0.28072727 | O536: 13.75 | P536: 4.274 | Q536: =K536-P536 -> 2.718 | R536: 83.97 | S536: =(O536*T536) -> 71.5 | T536: 5.2 | U536: 973.21 | Y536: 979.05
A537: 536 | B537: 38461 | C537: 1519660 | D537: =C537/E537 -> 34735.086 | E537: 43.75 | F537: =(D537/100000) -> 0.34735086 | G537: =(F537/'Yearly GDP'!$B$4)*100 -> 48.981296 | H537: =(K537/I537) -> 0.9644844 | I537: =(J537/L537)*100 -> 7.3313783 | J537: =L537/O537 -> 139.98534 | K537: 7.071 | L537: 1909.4 | M537: 3.57 | N537: =K537-I537 -> -0.2603783 | O537: 13.64 | P537: 4.217 | Q537: =K537-P537 -> 2.854 | R537: 83.71 | S537: =(O537*T537) -> 69.564 | T537: 5.1 | U537: 972.33 | Y537: 973.67
... A715: 714 | B715: 38716 | C715: 2322392 | D715: =C715/E715 -> 51614.446 | E715: 44.995 | F715: =(D715/100000) -> 0.51614446 | G715: =(F715/'Yearly GDP'!$B$4)*100 -> 72.783538 | H715: =(K715/I715) -> 1.220076 | I715: =(J715/L715)*100 -> 5.8275058 | J715: =L715/O715 -> 165.30012 | K715: 7.11 | L715: 2836.55 | M715: 4.37 | N715: =K715-I715 -> 1.2824942 | O715: 17.16 | P715: 4.395 | Q715: =K715-P715 -> 2.715 | R715: 90.96 | S715: =(O715*T715) -> 104.3328 | T715: 6.08 | U715: 1414.17 | Y715: 1537.75
A716: 715 | B716: 38719 | C716: 2327980 | D716: =C716/E716 -> 51646.811 | E716: 45.075 | F716: =(D716/100000) -> 0.51646811 | G716: =(F716/'Yearly GDP'!$B$5)*100 -> 62.954742 | H716: =(K716/I716) -> 1.232088 | I716: =(J716/L716)*100 -> 5.8275058 | J716: =L716/O716 -> 165.26515 | K716: 7.18 | L716: 2835.95 | M716: 4.37 | N716: =K716-I716 -> 1.3524942 | O716: 17.16 | P716: 4.395 | Q716: =K716-P716 -> 2.785 | R716: 90.96 | S716: =(O716*T716) -> 103.6464 | T716: 6.04 | U716: 1432.33 | Y716: 1562.08
A717: 716 | B717: 38720 | C717: 2363796 | D717: =C717/E717 -> 52569.688 | E717: 44.965 | F717: =(D717/100000) -> 0.52569688 | G717: =(F717/'Yearly GDP'!$B$5)*100 -> 64.07968 | H717: =(K717/I717) -> 1.25291 | I717: =(J717/L717)*100 -> 5.730659 | J717: =L717/O717 -> 165.23496 | K717: 7.18 | L717: 2883.35 | M717: 4.44 | N717: =K717-I717 -> 1.449341 | O717: 17.45 | P717: 4.37 | Q717: =K717-P717 -> 2.81 | R717: 89.57 | S717: =(O717*T717) -> 103.8275 | T717: 5.95 | U717: 1453.7 | Y717: 1591.64
A718: 717 | B718: 38721 | C718: 2383590 | D718: =C718/E718 -> 53318.197 | E718: 44.705 | F718: =(D718/100000) -> 0.53318197 | G718: =(F718/'Yearly GDP'!$B$5)*100 -> 64.992073 | H718: =(K718/I718) -> 1.2638262 | I718: =(J718/L718)*100 -> 5.6882821 | J718: =L718/O718 -> 165.21047 | K718: 7.189 | L718: 2904.4 | M718: 4.48 | N718: =K718-I718 -> 1.5007179 | O718: 17.58 | P718: 4.348 | Q718: =K718-P718 -> 2.841 | R718: 88.91 | S718: =(O718*T718) -> 104.601 | T718: 5.95 | U718: 1460.52 | Y718: 1598.88
A719: 718 | B719: 38722 | C719: 2386410 | D719: =C719/E719 -> 53506.951 | E719: 44.6 | F719: =(D719/100000) -> 0.53506951 | G719: =(F719/'Yearly GDP'!$B$5)*100 -> 65.222154 | H719: =(K719/I719) -> 1.259388 | I719: =(J719/L719)*100 -> 5.6980057 | J719: =L719/O719 -> 165.23362 | K719: 7.176 | L719: 2899.85 | M719: 4.47 | N719: =K719-I719 -> 1.4779943 | O719: 17.55 | P719: 4.358 | Q719: =K719-P719 -> 2.818 | R719: 89.08 | S719: =(O719*T719) -> 104.0715 | T719: 5.93 | U719: 1467 | Y719: 1596.55
A720: 719 | B720: 38723 | C720: 2404152 | D720: =C720/E720 -> 54245.307 | E720: 44.32 | F720: =(D720/100000) -> 0.54245307 | G720: =(F720/'Yearly GDP'!$B$5)*100 -> 66.122171 | H720: =(K720/I720) -> 1.2670812 | I720: =(J720/L720)*100 -> 5.6689342 | J720: =L720/O720 -> 165.19274 | K720: 7.183 | L720: 2914 | M720: 4.49 | N720: =K720-I720 -> 1.5140658 | O720: 17.64 | P720: 4.383 | Q720: =K720-P720 -> 2.8 | R720: 88.62 | S720: =(O720*T720) -> 105.3108 | T720: 5.97 | U720: 1478.04 | Y720: 1608.64
A721: 720 | B721: 38726 | C721: 2407877 | D721: =C721/E721 -> 54415.299 | E721: 44.25 | F721: =(D721/100000) -> 0.54415299 | G721: =(F721/'Yearly GDP'!$B$5)*100 -> 66.329383 | H721: =(K721/I721) -> 1.2663494 | I721: =(J721/L721)*100 -> 5.6753689 | J721: =L721/O721 -> 165.15891 | K721: 7.187 | L721: 2910.1 | M721: 4.49 | N721: =K721-I721 -> 1.5116311 | O721: 17.62 | P721: 4.373 | Q721: =K721-P721 -> 2.814 | R721: 89 | S721: =(O721*T721) -> 105.72 | T721: 6 | U721: 1490.27 | Y721: 1616.55
A722: 721 | B722: 38727 | C722: 2381047 | D722: =C722/E722 -> 53888.129 | E722: 44.185 | F722: =(D722/100000) -> 0.53888129 | G722: =(F722/'Yearly GDP'!$B$5)*100 -> 65.686791 | H722: =(K722/I722) -> 1.2485556 | I722: =(J722/L722)*100 -> 5.7570524 | J722: =L722/O722 -> 165.27346 | K722: 7.188 | L722: 2870.8 | M722: 4.43 | N722: =K722-I722 -> 1.4309476 | O722: 17.37 | P722: 4.43 | Q722: =K722-P722 -> 2.758 | R722: 89.07 | S722: =(O722*T722) -> 107.1729 | T722: 6.17 | U722: 1482.24 | Y722: 1604.62
A723: 722 | B723: 38729 | C723: 2372220 | D723: =C723/E723 -> 53889.596 | E723: 44.02 | F723: =(D723/100000) -> 0.53889596 | G723: =(F723/'Yearly GDP'!$B$5)*100 -> 65.688578 | H723: =(K723/I723) -> 1.2434688 | I723: =(J723/L723)*100 -> 5.787037 | J723: =L723/O723 -> 164.97106 | K723: 7.196 | L723: 2850.7 | M723: 4.4 | N723: =K723-I723 -> 1.408963 | O723: 17.28 | P723: 4.408 | Q723: =K723-P723 -> 2.788 | R723: 89.23 | S723: =(O723*T723) -> 106.0992 | T723: 6.14 | U723: 1481.49 | Y723: 1612.44
A724: 723 | B724: 38730 | C724: 2376100 | D724: =C724/E724 -> 53879.819 | E724: 44.1 | F724: =(D724/100000) -> 0.53879819 | G724: =(F724/'Yearly GDP'!$B$5)*100 -> 65.67666 | H724: =(K724/I724) -> 1.2442425 | I724: =(J724/L724)*100 -> 5.7971014 | J724: =L724/O724 -> 165.24928 | K724: 7.213 | L724: 2850.55 | M724: 4.4 | N724: =K724-I724 -> 1.4158986 | O724: 17.25 | P724: 4.357 | Q724: =K724-P724 -> 2.856 | R724: 88.66 | S724: =(O724*T724) -> 106.4325 | T724: 6.17 | U724: 1485.01 | Y724: 1622.82
A725: 724 | B725: 38733 | C725: 2360600 | D725: =C725/E725 -> 53443.514 | E725: 44.17 | F725: =(D725/100000) -> 0.53443514 | G725: =(F725/'Yearly GDP'!$B$5)*100 -> 65.144828 | H725: =(K725/I725) -> 1.2344228 | I725: =(J725/L725)*100 -> 5.8343057 | J725: =L725/O725 -> 165.29172 | K725: 7.202 | L725: 2833.1 | M725: 4.37 | N725: =K725-I725 -> 1.3676943 | O725: 17.14 | P725: 4.367 | Q725: =K725-P725 -> 2.835 | R725: 88.66 | S725: =(O725*T725) -> 105.9252 | T725: 6.18 | U725: 1479.43 | Y725: 1609.89
A726: 725 | B726: 38734 | C726: 2348829 | D726: =C726/E726 -> 53092.88 | E726: 44.24 | F726: =(D726/100000) -> 0.5309288 | G726: =(F726/'Yearly GDP'!$B$5)*100 -> 64.717423 | H726: =(K726/I726) -> 1.230928 | I726: =(J726/L726)*100 -> 5.8411215 | J726: =L726/O726 -> 165.25117 | K726: 7.19 | L726: 2829.1 | M726: 4.36 | N726: =K726-I726 -> 1.3488785 | O726: 17.12 | P726: 4.33 | Q726: =K726-P726 -> 2.86 | R726: 89.08 | S726: =(O726*T726) -> 106.4864 | T726: 6.22 | U726: 1465.52 | Y726: 1596.01
A727: 726 | B727: 38735 | C727: 2302657 | D727: =C727/E727 -> 51978.713 | E727: 44.3 | F727: =(D727/100000) -> 0.51978713 | G727: =(F727/'Yearly GDP'!$B$5)*100 -> 63.359313 | H727: =(K727/I727) -> 1.1903253 | I727: =(J727/L727)*100 -> 6.0496068 | J727: =L727/O727 -> 169.94555 | K727: 7.201 | L727: 2809.2 | M727: 4.24 | N727: =K727-I727 -> 1.1513932 | O727: 16.53 | P727: 4.338 | Q727: =K727-P727 -> 2.863 | R727: 89.08 | S727: =(O727*T727) -> 102.486 | T727: 6.2 | U727: 1456.66 | Y727: 1580.45
... A964: 963 | B964: 39080 | C964: 3426000 | D964: =C964/E964 -> 77660.66 | E964: 44.115 | F964: =(D964/100000) -> 0.7766066 | G964: =(F964/'Yearly GDP'!$B$5)*100 -> 94.664253 | H964: =(K964/I964) -> 1.6197994 | I964: =(J964/L964)*100 -> 4.7036689 | J964: =L964/O964 -> 186.56632 | K964: 7.619 | L964: 3966.4 | M964: 5.07 | N964: =K964-I964 -> 2.9153311 | O964: 21.26 | P964: 4.7 | Q964: =K964-P964 -> 2.919 | R964: 83.43 | S964: =(O964*T964) -> 152.6468 | T964: 7.18 | U964: 1795.28 | Y964: 2014.87
A965: 964 | B965: 39084 | C965: 3458000 | D965: =C965/E965 -> 78323.896 | E965: 44.15 | F965: =(D965/100000) -> 0.78323896 | G965: =(F965/'Yearly GDP'!$B$6)*100 -> 83.300253 | H965: =(K965/I965) -> 1.6187328 | I965: =(J965/L965)*100 -> 4.6554935 | J965: =L965/O965 -> 186.56425 | K965: 7.536 | L965: 4007.4 | M965: 5.12 | N965: =K965-I965 -> 2.8805065 | O965: 21.48 | P965: 4.684 | Q965: =K965-P965 -> 2.852 | R965: 82.97 | S965: =(O965*T965) -> 152.7228 | T965: 7.11 | U965: 1818.14 | Y965: 2044.77
A966: 965 | B966: 39085 | C966: 3479000 | D966: =C966/E966 -> 78621.469 | E966: 44.25 | F966: =(D966/100000) -> 0.78621469 | G966: =(F966/'Yearly GDP'!$B$6)*100 -> 83.616733 | H966: =(K966/I966) -> 1.626378 | I966: =(J966/L966)*100 -> 4.6360686 | J966: =L966/O966 -> 186.55772 | K966: 7.54 | L966: 4024.05 | M966: 5.14 | N966: =K966-I966 -> 2.9039314 | O966: 21.57 | P966: 4.664 | Q966: =K966-P966 -> 2.876 | R966: 83.68 | S966: =(O966*T966) -> 152.0685 | T966: 7.05 | U966: 1837.41 | Y966: 2069.87
A967: 966 | B967: 39086 | C967: 3465000 | D967: =C967/E967 -> 78446.91 | E967: 44.17 | F967: =(D967/100000) -> 0.7844691 | G967: =(F967/'Yearly GDP'!$B$6)*100 -> 83.431083 | H967: =(K967/I967) -> 1.6214592 | I967: =(J967/L967)*100 -> 4.6772685 | J967: =L967/O967 -> 186.56688 | K967: 7.584 | L967: 3988.8 | M967: 5.1 | N967: =K967-I967 -> 2.9067315 | O967: 21.38 | P967: 4.608 | Q967: =K967-P967 -> 2.976 | R967: 84.09 | S967: =(O967*T967) -> 150.729 | T967: 7.05 | U967: 1842.54 | Y967: 2084.31
A968: 967 | B968: 39087 | C968: 3466000 | D968: =C968/E968 -> 78442.91 | E968: 44.185 | F968: =(D968/100000) -> 0.7844291 | G968: =(F968/'Yearly GDP'!$B$6)*100 -> 83.426829 | H968: =(K968/I968) -> 1.6129925 | I968: =(J968/L968)*100 -> 4.6838407 | J968: =L968/O968 -> 186.57611 | K968: 7.555 | L968: 3983.4 | M968: 5.09 | N968: =K968-I968 -> 2.8711593 | O968: 21.35 | P968: 4.648 | Q968: =K968-P968 -> 2.907 | R968: 84.4 | S968: =(O968*T968) -> 150.5175 | T968: 7.05 | U968: 1842.47 | Y968: 2095.68
A969: 968 | B969: 39090 | C969: 3430000 | D969: =C969/E969 -> 77374.239 | E969: 44.33 | F969: =(D969/100000) -> 0.77374239 | G969: =(F969/'Yearly GDP'!$B$6)*100 -> 82.290259 | H969: =(K969/I969) -> 1.578892 | I969: =(J969/L969)*100 -> 4.743833 | J969: =L969/O969 -> 186.59393 | K969: 7.49 | L969: 3933.4 | M969: 5.03 | N969: =K969-I969 -> 2.746167 | O969: 21.08 | P969: 4.658 | Q969: =K969-P969 -> 2.832 | R969: 84.37 | S969: =(O969*T969) -> 148.614 | T969: 7.05 | U969: 1832.67 | Y969: 2102.84
A970: 969 | B970: 39091 | C970: 3430000 | D970: =C970/E970 -> 77461.608 | E970: 44.28 | F970: =(D970/100000) -> 0.77461608 | G970: =(F970/'Yearly GDP'!$B$6)*100 -> 82.383179 | H970: =(K970/I970) -> 1.574847 | I970: =(J970/L970)*100 -> 4.7687172 | J970: =L970/O970 -> 186.52361 | K970: 7.51 | L970: 3911.4 | M970: 5 | N970: =K970-I970 -> 2.7412828 | O970: 20.97 | P970: 4.662 | Q970: =K970-P970 -> 2.848 | R970: 84.52 | S970: =(O970*T970) -> 147.4191 | T970: 7.03 | U970: 1824.53 | Y970: 2091.24
A971: 970 | B971: 39092 | C971: 3433000 | D971: =C971/E971 -> 77232.846 | E971: 44.45 | F971: =(D971/100000) -> 0.77232846 | G971: =(F971/'Yearly GDP'!$B$6)*100 -> 82.139882 | H971: =(K971/I971) -> 1.5556368 | I971: =(J971/L971)*100 -> 4.8449612 | J971: =L971/O971 -> 186.54554 | K971: 7.537 | L971: 3850.3 | M971: 4.92 | N971: =K971-I971 -> 2.6920388 | O971: 20.64 | P971: 4.69 | Q971: =K971-P971 -> 2.847 | R971: 84.85 | S971: =(O971*T971) -> 145.7184 | T971: 7.06 | U971: 1805.07 | Y971: 2073.49
A972: 971 | B972: 39093 | C972: 3458000 | D972: =C972/E972 -> 77707.865 | E972: 44.5 | F972: =(D972/100000) -> 0.77707865 | G972: =(F972/'Yearly GDP'!$B$6)*100 -> 82.645082 | H972: =(K972/I972) -> 1.5857848 | I972: =(J972/L972)*100 -> 4.7528517 | J972: =L972/O972 -> 187.3693 | K972: 7.537 | L972: 3942.25 | M972: 5.04 | N972: =K972-I972 -> 2.7841483 | O972: 21.04 | P972: 4.739 | Q972: =K972-P972 -> 2.798 | R972: 85.09 | S972: =(O972*T972) -> 148.7528 | T972: 7.07 | U972: 1828.55 | Y972: 2105.32
A973: 972 | B973: 39094 | C973: 3536000 | D973: =C973/E973 -> 79792.395 | E973: 44.315 | F973: =(D973/100000) -> 0.79792395 | G973: =(F973/'Yearly GDP'!$B$6)*100 -> 84.862054 | H973: =(K973/I973) -> 1.7146101 | I973: =(J973/L973)*100 -> 4.6232085 | J973: =L973/O973 -> 187.35321 | K973: 7.927 | L973: 4052.45 | M973: 5.16 | N973: =K973-I973 -> 3.3037915 | O973: 21.63 | P973: 4.783 | Q973: =K973-P973 -> 3.144 | R973: 84.82 | S973: =(O973*T973) -> 152.9241 | T973: 7.07 | U973: 1854.13 | Y973: 2130.7
A974: 973 | B974: 39097 | C974: 3565340 | D974: =C974/E974 -> 80645.555 | E974: 44.21 | F974: =(D974/100000) -> 0.80645555 | G974: =(F974/'Yearly GDP'!$B$6)*100 -> 85.76942 | H974: =(K974/I974) -> 1.6963184 | I974: =(J974/L974)*100 -> 4.5934773 | J974: =L974/O974 -> 187.34038 | K974: 7.792 | L974: 4078.4 | M974: 5.19 | N974: =K974-I974 -> 3.1985227 | O974: 21.77 | P974: 4.646 | Q974: =K974-P974 -> 3.146 | R974: 84.82 | S974: =(O974*T974) -> 154.567 | T974: 7.1 | U974: 1869.9 | Y974: 2161.9
A975: 974 | B975: 39098 | C975: 3565340 | D975: =C975/E975 -> 80663.801 | E975: 44.2 | F975: =(D975/100000) -> 0.80663801 | G975: =(F975/'Yearly GDP'!$B$6)*100 -> 85.788825 | H975: =(K975/I975) -> 1.6828922 | I975: =(J975/L975)*100 -> 4.6146747 | J975: =L975/O975 -> 188.3018 | K975: 7.766 | L975: 4080.5 | M975: 5.19 | N975: =K975-I975 -> 3.1513253 | O975: 21.67 | P975: 4.753 | Q975: =K975-P975 -> 3.013 | R975: 84.85 | S975: =(O975*T975) -> 152.7735 | T975: 7.05 | U975: 1877.68 | Y975: 2171.27
A976: 975 | B976: 39099 | C976: 3567150 | D976: =C976/E976 -> 80887.755 | E976: 44.1 | F976: =(D976/100000) -> 0.80887755 | G976: =(F976/'Yearly GDP'!$B$6)*100 -> 86.027009 | H976: =(K976/I976) -> 1.686179 | I976: =(J976/L976)*100 -> 4.631774 | J976: =L976/O976 -> 188.81195 | K976: 7.81 | L976: 4076.45 | M976: 5.19 | N976: =K976-I976 -> 3.178226 | O976: 21.59 | P976: 4.785 | Q976: =K976-P976 -> 3.025 | R976: 84.76 | S976: =(O976*T976) -> 153.289 | T976: 7.1 | U976: 1885.53 | Y976: 2189.64
... A1206: 1205 | B1206: 39447 | C1206: 6543272 | D1206: =C1206/E1206 -> 166051.82 | E1206: 39.405 | F1206: =(D1206/100000) -> 1.6605182 | G1206: =(F1206/'Yearly GDP'!$B$6)*100 -> 176.60203 | H1206: =(K1206/I1206) -> 2.1518742 | I1206: =(J1206/L1206)*100 -> 3.6205648 | J1206: =L1206/O1206 -> 222.25199 | K1206: 7.791 | L1206: 6138.6 | M1206: 6.39 | N1206: =K1206-I1206 -> 4.1704352 | O1206: 27.62 | P1206: 4.035 | Q1206: =K1206-P1206 -> 3.756 | R1206: 76.7 | S1206: =(O1206*T1206) -> 203.8356 | T1206: 7.38 | U1206: 3162.15 | Y1206: 3927.98
A1207: 1206 | B1207: 39448 | C1207: 6584491.2 | D1207: =C1207/E1207 -> 167055.47 | E1207: 39.415 | F1207: =(D1207/100000) -> 1.6705547 | G1207: =(F1207/'Yearly GDP'!$B$7)*100 -> 136.93071 | H1207: =(K1207/I1207) -> 2.1409944 | I1207: =(J1207/L1207)*100 -> 3.617945 | J1207: =L1207/O1207 -> 222.2992 | K1207: 7.746 | L1207: 6144.35 | M1207: 6.4 | N1207: =K1207-I1207 -> 4.128055 | O1207: 27.64 | P1207: 4.035 | Q1207: =K1207-P1207 -> 3.711 | R1207: 76.7 | S1207: =(O1207*T1207) -> 201.772 | T1207: 7.3 | U1207: 3220.99 | Y1207: 4004.14
A1208: 1207 | B1208: 39449 | C1208: 6652066 | D1208: =C1208/E1208 -> 169199.19 | E1208: 39.315 | F1208: =(D1208/100000) -> 1.6919919 | G1208: =(F1208/'Yearly GDP'!$B$7)*100 -> 138.68786 | H1208: =(K1208/I1208) -> 2.153388 | I1208: =(J1208/L1208)*100 -> 3.5971223 | J1208: =L1208/O1208 -> 222.28058 | K1208: 7.746 | L1208: 6179.4 | M1208: 6.43 | N1208: =K1208-I1208 -> 4.1488777 | O1208: 27.8 | P1208: 3.905 | Q1208: =K1208-P1208 -> 3.841 | R1208: 76.01 | S1208: =(O1208*T1208) -> 196.824 | T1208: 7.08 | U1208: 3282.05 | Y1208: 4039.14
A1209: 1208 | B1209: 39450 | C1209: 6670933 | D1209: =C1209/E1209 -> 170068.4 | E1209: 39.225 | F1209: =(D1209/100000) -> 1.700684 | G1209: =(F1209/'Yearly GDP'!$B$7)*100 -> 139.40033 | H1209: =(K1209/I1209) -> 2.15589 | I1209: =(J1209/L1209)*100 -> 3.5971223 | J1209: =L1209/O1209 -> 222.25 | K1209: 7.755 | L1209: 6178.55 | M1209: 6.43 | N1209: =K1209-I1209 -> 4.1578777 | O1209: 27.8 | P1209: 3.894 | Q1209: =K1209-P1209 -> 3.861 | R1209: 75.92 | S1209: =(O1209*T1209) -> 194.044 | T1209: 6.98 | U1209: 3284.43 | Y1209: 4030.16
A1210: 1209 | B1210: 39451 | C1210: 6742692 | D1210: =C1210/E1210 -> 171482.5 | E1210: 39.32 | F1210: =(D1210/100000) -> 1.714825 | G1210: =(F1210/'Yearly GDP'!$B$7)*100 -> 140.55943 | H1210: =(K1210/I1210) -> 2.1754038 | I1210: =(J1210/L1210)*100 -> 3.5423309 | J1210: =L1210/O1210 -> 222.25646 | K1210: 7.706 | L1210: 6274.3 | M1210: 6.53 | N1210: =K1210-I1210 -> 4.1636691 | O1210: 28.23 | P1210: 3.875 | Q1210: =K1210-P1210 -> 3.831 | R1210: 75.82 | S1210: =(O1210*T1210) -> 197.61 | T1210: 7 | U1210: 3306.04 | Y1210: 4038.1
A1211: 1210 | B1211: 39454 | C1211: 6745724 | D1211: =C1211/E1211 -> 171843.69 | E1211: 39.255 | F1211: =(D1211/100000) -> 1.7184369 | G1211: =(F1211/'Yearly GDP'!$B$7)*100 -> 140.85548 | H1211: =(K1211/I1211) -> 2.16395 | I1211: =(J1211/L1211)*100 -> 3.539823 | J1211: =L1211/O1211 -> 222.26903 | K1211: 7.66 | L1211: 6279.1 | M1211: 6.54 | N1211: =K1211-I1211 -> 4.120177 | O1211: 28.25 | P1211: 3.837 | Q1211: =K1211-P1211 -> 3.823 | R1211: 76.2 | S1211: =(O1211*T1211) -> 197.75 | T1211: 7 | U1211: 3330.91 | Y1211: 4034.63
A1212: 1211 | B1212: 39455 | C1212: 6683436 | D1212: =C1212/E1212 -> 170757.18 | E1212: 39.14 | F1212: =(D1212/100000) -> 1.7075718 | G1212: =(F1212/'Yearly GDP'!$B$7)*100 -> 139.9649 | H1212: =(K1212/I1212) -> 2.1706917 | I1212: =(J1212/L1212)*100 -> 3.534818 | J1212: =L1212/O1212 -> 222.26405 | K1212: 7.673 | L1212: 6287.85 | M1212: 6.55 | N1212: =K1212-I1212 -> 4.138182 | O1212: 28.29 | P1212: 3.78 | Q1212: =K1212-P1212 -> 3.893 | R1212: 76.12 | S1212: =(O1212*T1212) -> 193.7865 | T1212: 6.85 | U1212: 3258.37 | Y1212: 3918.78
A1213: 1212 | B1213: 39456 | C1213: 6663394 | D1213: =C1213/E1213 -> 170093.02 | E1213: 39.175 | F1213: =(D1213/100000) -> 1.7009302 | G1213: =(F1213/'Yearly GDP'!$B$7)*100 -> 139.42051 | H1213: =(K1213/I1213) -> 2.1599588 | I1213: =(J1213/L1213)*100 -> 3.5435861 | J1213: =L1213/O1213 -> 222.25372 | K1213: 7.654 | L1213: 6272 | M1213: 6.53 | N1213: =K1213-I1213 -> 4.1104139 | O1213: 28.22 | P1213: 3.825 | Q1213: =K1213-P1213 -> 3.829 | R1213: 76.46 | S1213: =(O1213*T1213) -> 196.129 | T1213: 6.95 | U1213: 3224.84 | Y1213: 3892.79
A1214: 1213 | B1214: 39457 | C1214: 6488778 | D1214: =C1214/E1214 -> 165614.55 | E1214: 39.18 | F1214: =(D1214/100000) -> 1.6561455 | G1214: =(F1214/'Yearly GDP'!$B$7)*100 -> 135.74963 | H1214: =(K1214/I1214) -> 2.101322 | I1214: =(J1214/L1214)*100 -> 3.6101083 | J1214: =L1214/O1214 -> 222.27256 | K1214: 7.586 | L1214: 6156.95 | M1214: 6.41 | N1214: =K1214-I1214 -> 3.9758917 | O1214: 27.7 | P1214: 3.889 | Q1214: =K1214-P1214 -> 3.697 | R1214: 76 | S1214: =(O1214*T1214) -> 193.9 | T1214: 7 | U1214: 3100.45 | Y1214: 3761.74
A1215: 1214 | B1215: 39458 | C1215: 6519967 | D1215: =C1215/E1215 -> 166453.08 | E1215: 39.17 | F1215: =(D1215/100000) -> 1.6645308 | G1215: =(F1215/'Yearly GDP'!$B$7)*100 -> 136.43695 | H1215: =(K1215/I1215) -> 2.1070518 | I1215: =(J1215/L1215)*100 -> 3.5893754 | J1215: =L1215/O1215 -> 222.54487 | K1215: 7.563 | L1215: 6200.1 | M1215: 6.46 | N1215: =K1215-I1215 -> 3.9736246 | O1215: 27.86 | P1215: 3.791 | Q1215: =K1215-P1215 -> 3.772 | R1215: 76.04 | S1215: =(O1215*T1215) -> 195.02 | T1215: 7 | U1215: 3088.44 | Y1215: 3741.75
A1216: 1215 | B1216: 39461 | C1216: 6568150 | D1216: =C1216/E1216 -> 167149.76 | E1216: 39.295 | F1216: =(D1216/100000) -> 1.6714976 | G1216: =(F1216/'Yearly GDP'!$B$7)*100 -> 137.008 | H1216: =(K1216/I1216) -> 2.1040216 | I1216: =(J1216/L1216)*100 -> 3.5855145 | J1216: =L1216/O1216 -> 222.54572 | K1216: 7.544 | L1216: 6206.8 | M1216: 6.47 | N1216: =K1216-I1216 -> 3.9584855 | O1216: 27.89 | P1216: 3.772 | Q1216: =K1216-P1216 -> 3.772 | R1216: 75.7 | S1216: =(O1216*T1216) -> 195.23 | T1216: 7 | U1216: 3131.36 | Y1216: 3778
A1217: 1216 | B1217: 39462 | C1217: 6449402 | D1217: =C1217/E1217 -> 164295.05 | E1217: 39.255 | F1217: =(D1217/100000) -> 1.6429505 | G1217: =(F1217/'Yearly GDP'!$B$7)*100 -> 134.66807 | H1217: =(K1217/I1217) -> 2.062788 | I1217: =(J1217/L1217)*100 -> 3.6630037 | J1217: =L1217/O1217 -> 222.5 | K1217: 7.556 | L1217: 6074.25 | M1217: 6.33 | N1217: =K1217-I1217 -> 3.8929963 | O1217: 27.3 | P1217: 3.681 | Q1217: =K1217-P1217 -> 3.875 | R1217: 75.66 | S1217: =(O1217*T1217) -> 189.735 | T1217: 6.95 | U1217: 3098.75 | Y1217: 3741.76
A1218: 1217 | B1218: 39463 | C1218: 6310012 | D1218: =C1218/E1218 -> 160928.64 | E1218: 39.21 | F1218: =(D1218/100000) -> 1.6092864 | G1218: =(F1218/'Yearly GDP'!$B$7)*100 -> 131.90872 | H1218: =(K1218/I1218) -> 2.0170521 | I1218: =(J1218/L1218)*100 -> 3.7495313 | J1218: =L1218/O1218 -> 222.5628 | K1218: 7.563 | L1218: 5935.75 | M1218: 6.18 | N1218: =K1218-I1218 -> 3.8134687 | O1218: 26.67 | P1218: 3.74 | Q1218: =K1218-P1218 -> 3.823 | R1218: 76.36 | S1218: =(O1218*T1218) -> 188.0235 | T1218: 7.05 | U1218: 3043.59 | Y1218: 3658.13
... A1452: 1451 | B1452: 39813 | C1452: 2916768 | D1452: =C1452/E1452 -> 59991.115 | E1452: 48.62 | F1452: =(D1452/100000) -> 0.59991115 | G1452: =(F1452/'Yearly GDP'!$B$7)*100 -> 49.173045 | H1452: =(K1452/I1452) -> 0.682222 | I1452: =(J1452/L1452)*100 -> 7.7101002 | J1452: =L1452/O1452 -> 228.15343 | K1452: 5.26 | L1452: 2959.15 | M1452: 2.44 | N1452: =K1452-I1452 -> -2.4501002 | O1452: 12.97 | P1452: 2.22 | Q1452: =K1452-P1452 -> 3.04 | R1452: 82.15 | S1452: =(O1452*T1452) -> 62.9045 | T1452: 4.85 | U1452: 1091.51 | Y1452: 1214.54
A1453: 1452 | B1453: 39814 | C1453: 2999733 | D1453: =C1453/E1453 -> 61532.985 | E1453: 48.75 | F1453: =(D1453/100000) -> 0.61532985 | G1453: =(F1453/'Yearly GDP'!$B$8)*100 -> 51.277487 | H1453: =(K1453/I1453) -> 0.701575 | I1453: =(J1453/L1453)*100 -> 7.518797 | J1453: =L1453/O1453 -> 228.07895 | K1453: 5.275 | L1453: 3033.45 | M1453: 2.5 | N1453: =K1453-I1453 -> -2.243797 | O1453: 13.3 | P1453: 2.22 | Q1453: =K1453-P1453 -> 3.055 | R1453: 82.15 | S1453: =(O1453*T1453) -> 60.249 | T1453: 4.53 | U1453: 1119.07 | Y1453: 1248.99
A1454: 1453 | B1454: 39815 | C1454: 3025460 | D1454: =C1454/E1454 -> 62873.234 | E1454: 48.12 | F1454: =(D1454/100000) -> 0.62873234 | G1454: =(F1454/'Yearly GDP'!$B$8)*100 -> 52.394361 | H1454: =(K1454/I1454) -> 0.7146264 | I1454: =(J1454/L1454)*100 -> 7.4850299 | J1454: =L1454/O1454 -> 228.05015 | K1454: 5.349 | L1454: 3046.75 | M1454: 2.51 | N1454: =K1454-I1454 -> -2.1360299 | O1454: 13.36 | P1454: 2.361 | Q1454: =K1454-P1454 -> 2.988 | R1454: 82.805 | S1454: =(O1454*T1454) -> 56.112 | T1454: 4.2 | U1454: 1143.67 | Y1454: 1270.88
A1455: 1454 | B1455: 39818 | C1455: 3092923 | D1455: =C1455/E1455 -> 63890.167 | E1455: 48.41 | F1455: =(D1455/100000) -> 0.63890167 | G1455: =(F1455/'Yearly GDP'!$B$8)*100 -> 53.241806 | H1455: =(K1455/I1455) -> 0.7075296 | I1455: =(J1455/L1455)*100 -> 7.3099415 | J1455: =L1455/O1455 -> 228.17617 | K1455: 5.172 | L1455: 3121.45 | M1455: 2.58 | N1455: =K1455-I1455 -> -2.1379415 | O1455: 13.68 | P1455: 2.485 | Q1455: =K1455-P1455 -> 2.687 | R1455: 83.575 | S1455: =(O1455*T1455) -> 58.14 | T1455: 4.25 | U1455: 1162.46 | Y1455: 1291.01
A1456: 1455 | B1456: 39819 | C1456: 3088624 | D1456: =C1456/E1456 -> 63761.85 | E1456: 48.44 | F1456: =(D1456/100000) -> 0.6376185 | G1456: =(F1456/'Yearly GDP'!$B$8)*100 -> 53.134875 | H1456: =(K1456/I1456) -> 0.7219652 | I1456: =(J1456/L1456)*100 -> 7.3313783 | J1456: =L1456/O1456 -> 228.21114 | K1456: 5.293 | L1456: 3112.8 | M1456: 2.57 | N1456: =K1456-I1456 -> -2.0383783 | O1456: 13.64 | P1456: 2.45 | Q1456: =K1456-P1456 -> 2.843 | R1456: 83.72 | S1456: =(O1456*T1456) -> 58.652 | T1456: 4.3 | U1456: 1155.78 | Y1456: 1293.15
A1457: 1456 | B1457: 39820 | C1457: 2886033 | D1457: =C1457/E1457 -> 59218.898 | E1457: 48.735 | F1457: =(D1457/100000) -> 0.59218898 | G1457: =(F1457/'Yearly GDP'!$B$8)*100 -> 49.349082 | H1457: =(K1457/I1457) -> 0.765696 | I1457: =(J1457/L1457)*100 -> 7.8125 | J1457: =L1457/O1457 -> 228.15625 | K1457: 5.982 | L1457: 2920.4 | M1457: 2.41 | N1457: =K1457-I1457 -> -1.8305 | O1457: 12.8 | P1457: 2.498 | Q1457: =K1457-P1457 -> 3.484 | R1457: 83.115 | S1457: =(O1457*T1457) -> 57.6 | T1457: 4.5 | U1457: 1076.29 | Y1457: 1203.84
A1458: 1457 | B1458: 39822 | C1458: 2825802 | D1458: =C1458/E1458 -> 58785.147 | E1458: 48.07 | F1458: =(D1458/100000) -> 0.58785147 | G1458: =(F1458/'Yearly GDP'!$B$8)*100 -> 48.987622 | H1458: =(K1458/I1458) -> 0.7614432 | I1458: =(J1458/L1458)*100 -> 7.9428118 | J1458: =L1458/O1458 -> 228.19698 | K1458: 6.048 | L1458: 2873 | M1458: 2.37 | N1458: =K1458-I1458 -> -1.8948118 | O1458: 12.59 | P1458: 2.393 | Q1458: =K1458-P1458 -> 3.655 | R1458: 83.455 | S1458: =(O1458*T1458) -> 57.2845 | T1458: 4.55 | U1458: 1048.33 | Y1458: 1170.33
A1459: 1458 | B1459: 39825 | C1459: 2745075 | D1459: =C1459/E1459 -> 56459.79 | E1459: 48.62 | F1459: =(D1459/100000) -> 0.5645979 | G1459: =(F1459/'Yearly GDP'!$B$8)*100 -> 47.049825 | H1459: =(K1459/I1459) -> 0.720104 | I1459: =(J1459/L1459)*100 -> 8.1168831 | J1459: =L1459/O1459 -> 225.08929 | K1459: 5.845 | L1459: 2773.1 | M1459: 2.31 | N1459: =K1459-I1459 -> -2.2718831 | O1459: 12.32 | P1459: 2.309 | Q1459: =K1459-P1459 -> 3.536 | R1459: 83.745 | S1459: =(O1459*T1459) -> 56.056 | T1459: 4.55 | U1459: 1029.36 | Y1459: 1152.3
A1460: 1459 | B1460: 39826 | C1460: 2713907 | D1460: =C1460/E1460 -> 55470.761 | E1460: 48.925 | F1460: =(D1460/100000) -> 0.55470761 | G1460: =(F1460/'Yearly GDP'!$B$8)*100 -> 46.225634 | H1460: =(K1460/I1460) -> 0.6905664 | I1460: =(J1460/L1460)*100 -> 8.2236842 | J1460: =L1460/O1460 -> 225.73602 | K1460: 5.679 | L1460: 2744.95 | M1460: 2.28 | N1460: =K1460-I1460 -> -2.5446842 | O1460: 12.16 | P1460: 2.297 | Q1460: =K1460-P1460 -> 3.382 | R1460: 84.995 | S1460: =(O1460*T1460) -> 53.8688 | T1460: 4.43 | U1460: 1016.99 | Y1460: 1135.83
...

Sheet Buffett indicator
A1: Country Name | B1: India
A2: Country Code | B2: IND
A3: Indicator Name | B3: Market capitalization of listed domestic companies (% of GDP)
A4: Indicator Code | B4: Market cap to GDP
A5: 1960
A6: 1961
A7: 1962
A8: 1963
A9: 1964
A10: 1965
A11: 1966
A12: 1967
A13: 1968
A14: 1969
A15: 1970
A16: 1971
... A44: 1999
A45: 2000 | B45: 48.17475
A46: 2001 | B46: 30.646752
A47: 2002 | B47: 33.438061
A48: 2003 | B48: 50.846571
A49: 2004 | B49: 58.597294
A50: 2005 | B50: 76.152115
A51: 2006 | B51: 95.215152
A52: 2007 | B52: 161.23945
A53: 2008 | B53: 66.003104
A54: 2009 | B54: 101.89449
A55: 2010 | B55: 105.18295
A56: 2011 | B56: 68.270064
... A70: 2025 | B70: 137.7

Sheet Future return
B1: Year | C1: Nifty | D1: Nifty aft 5yr | E1: Future 5yr CAGR | I1: Valuation Bucket
B2: 2000 | C2: 1263.55 | D2: 2836.55 | E2: =(D2/C2)^(1/5)-1 -> 0.17554593 | I2: Score | J2: Bucket
B3: 2001 | C3: 1059.05 | D3: 3966.4 | E3: =(D3/C3)^(1/5)-1 -> 0.30225493 | I3: 0-20% | J3: Deep Value
B4: 2002 | C4: 1093.5 | D4: 6138.6 | E4: =(D4/C4)^(1/5)-1 -> 0.41205011 | I4: 20-40% | J4: Cheap
B5: 2003 | C5: 1879.75 | D5: 2959.15 | E5: =(D5/C5)^(1/5)-1 -> 0.09499813 | I5: 40-60% | J5: Fair
B6: 2004 | C6: 2080.5 | D6: 5201.05 | E6: =(D6/C6)^(1/5)-1 -> 0.2011152 | I6: 60-80% | J6: Expensive
B7: 2005 | C7: 2836.55 | D7: 6134.5 | E7: =(D7/C7)^(1/5)-1 -> 0.16680356 | I7: 80-100% | J7: Very Expensive
B8: 2006 | C8: 3966.4 | D8: 4624.3 | E8: =(D8/C8)^(1/5)-1 -> 0.031169119
B9: 2007 | C9: 6138.6 | D9: 5905.1 | E9: =(D9/C9)^(1/5)-1 -> -0.0077260631
B10: 2008 | C10: 2959.15 | D10: 6304 | E10: =(D10/C10)^(1/5)-1 -> 0.16329496
B11: 2009 | C11: 5201.05 | D11: 8282.7 | E11: =(D11/C11)^(1/5)-1 -> 0.097529445
B12: 2010 | C12: 6134.5 | D12: 7964.35 | E12: =(D12/C12)^(1/5)-1 -> 0.053596291
B13: 2011 | C13: 4624.3 | D13: 8185.8 | E13: =(D13/C13)^(1/5)-1 -> 0.12099332
B14: 2012 | C14: 5905.1 | D14: 10530.7 | E14: =(D14/C14)^(1/5)-1 -> 0.12265418
B15: 2013 | C15: 6304 | D15: 10862.55 | E15: =(D15/C15)^(1/5)-1 -> 0.11496983
B16: 2014 | C16: 8282.7 | D16: 12168.45 | E16: =(D16/C16)^(1/5)-1 -> 0.079972423
B17: 2015 | C17: 7964.35 | D17: 13981.75 | E17: =(D17/C17)^(1/5)-1 -> 0.11913438
B18: 2016 | C18: 8185.8 | D18: 17354.05 | E18: =(D18/C18)^(1/5)-1 -> 0.1621654
B19: 2017 | C19: 10530.7 | D19: 18105.3 | E19: =(D19/C19)^(1/5)-1 -> 0.11447337
... B22: 2020 | C22: 13981.75 | D22: 26129.6 | E22: =(D22/C22)^(1/5)-1 -> 0.13322004
B23: 2021 | C23: 17354.05
B24: 2022 | C24: 18105.3
B25: 2023 | C25: 21731.4
B26: 2024 | C26: 23644.8
B27: 2025 | C27: 26129.6

Sheet Yearly GDP
A1: Year | B1: (USD) in Trillions | C1: GDP | D1: CY changes
A2: 2002 | B2: =C2/1000 -> 0.51494 | C2: 514.94
A3: 2003 | B3: 0.6077 | C3: =B3*1000 -> 607.7 | D3: =(C3-C2)/C2 -> 0.18013749
A4: 2004 | B4: 0.70915 | C4: =B4*1000 -> 709.15 | D4: =(C4-C3)/C3 -> 0.16694092
A5: 2005 | B5: 0.82038 | C5: =B5*1000 -> 820.38 | D5: =(C5-C4)/C4 -> 0.15684975
A6: 2006 | B6: 0.94026 | C6: =B6*1000 -> 940.26 | D6: =(C6-C5)/C5 -> 0.1461274
A7: 2007 | B7: 1.22 | C7: =B7*1000 -> 1220 | D7: =(C7-C6)/C6 -> 0.29751345
A8: 2008 | B8: 1.2 | C8: =B8*1000 -> 1200 | D8: =(C8-C7)/C7 -> -0.016393443
A9: 2009 | B9: 1.34 | C9: =B9*1000 -> 1340 | D9: =(C9-C8)/C8 -> 0.11666667
A10: 2010 | B10: 1.68 | C10: =B10*1000 -> 1680 | D10: =(C10-C9)/C9 -> 0.25373134
A11: 2011 | B11: 1.82 | C11: =B11*1000 -> 1820 | D11: =(C11-C10)/C10 -> 0.083333333
A12: 2012 | B12: 1.83 | C12: =B12*1000 -> 1830 | D12: =(C12-C11)/C11 -> 0.0054945055
A13: 2013 | B13: 1.86 | C13: =B13*1000 -> 1860 | D13: =(C13-C12)/C12 -> 0.016393443
A14: 2014 | B14: 2.04 | C14: =B14*1000 -> 2040 | D14: =(C14-C13)/C13 -> 0.096774194
... A24: 2024 | B24: 3.68 | C24: =B24*1000 -> 3680 | D24: =(C24-C23)/C23 -> 0.030812325
A25: 2025

Sheet PE PB
A1: Date | B1: P/E | C1: P/B
A2: 36889 | B2: 19.2 | C2: 4.14
A3: 36888 | B3: 18.98 | C3: 4.09
A4: 36887 | B4: 18.67 | C4: 4.02
A5: 36886 | B5: 18.42 | C5: 3.97
A6: 36882 | B6: 18.87 | C6: 4.07
A7: 36881 | B7: 19.41 | C7: 4.18
A8: 36880 | B8: 19.68 | C8: 4.24
A9: 36879 | B9: 19.88 | C9: 4.28
A10: 36878 | B10: 19.98 | C10: 4.31
A11: 36875 | B11: 19.91 | C11: 4.29
A12: 36874 | B12: 20.47 | C12: 4.41
A13: 36873 | B13: 20.54 | C13: 4.43
... A6467: 45658 | B6467: 21.88 | C6467: 3.54
